Workbook

Sheet How to Use
B1: HOW TO USE THIS WORKBOOK
B3: STRUCTURE
B4: One master sheet - 'Use Case Library' - contains all 46 defence use cases with full detail. Policy sheets pull from it automatically via INDEX/MATCH. One input (UC ID in yellow cell) drives all lookups.
B6: ADDING A NEW POLICY (3 steps)
B7: 1. Right-click 'Policy - TEMPLATE' tab → Move or Copy → tick 'Create a copy'. Rename to 'Policy - UC-XXX'.
B8: 2. Type the UC ID in the yellow cell. All context auto-fills.
B9: 3. Fill in Decision Logic, Metrics, Edge Cases, Test Cases, and Sign-off manually.
B11: ADDING A NEW USE CASE
B12: Add a row in the Use Case Library after the appropriate group separator. Use the same column structure. Then create a policy sheet for it when ready.
B14: COLOUR CODING
B15: Group separator rows are colour-coded by domain. The Detection Modality column is colour-coded: green = Visual Only, amber = Visual-Primary Audio-Enhanced, red = Visual + Audio (required). The Modality Summary sheet provides a full breakdown.
B17: SMART LINKING
... B24: • Foundation use cases (UC-006, UC-008, UC-045) should be prioritised first - many others depend on them.

Sheet Use Case Library
A1: Status | B1: UC ID | C1: Group | D1: Category | E1: Use Case Name | F1: Description | G1: User Intent | H1: Trigger / Detection Method | I1: Key Behaviours to Track | J1: Desired Outcome | K1: Current Handling | L1: Edge Cases / Failure Modes | M1: Priority | N1: Policy / Algorithm Status | O1: Policy / Algorithm Summary | P1: Dependencies | Q1: Config Variables | R1: Detection Modality | S1: Modality Rationale | T1: Policy Sheet
B2: GROUP A: CORE SAFETY
A3: TRUE | B3: UC-001 | C3: A | D3: Core Safety | E3: Weapon Muzzle Direction Violation (Flagging) | F3: Detects when a weapon muzzle sweeps across another person or points in an unsafe direction relative to the designated firing arc. Must distinguish momentary transitions (low-ready to firing position) from sustained unsafe orientation. | G3: Never point your weapon at anything you don't intend to shoot - the most fundamental range safety rule. | H3: Pose estimation of firer + weapon orientation vector relative to other detected persons and safe arc boundaries. | I3: 1) Muzzle-to-person angular proximity 2) Duration of unsafe orientation (transient vs sustained) 3) Frequency per individual per session 4) Context: was the firer in motion or stationary? | J3: Immediate visual/audible alert to range safety officer with camera snapshot and firer location. By default: If no external system integration is needed, it will then route the notification and alert to Accel. | K3: Generic post-event review of CCTV - violations discovered after the fact, if at all. | L3: - Momentary sweep during weapon transition - Multiple people in frame - which is 'swept'? - Weapon with mounted optic obscures muzzle line - Prone position makes muzzle direction harder to resolve | M3: P0 - Critical | N3: Not Started | O3: Weapon Muzzle Direction Violation IF muzzle-to-person angle < 15° AND duration > 2s → ALERT (sustained sweep). IF angle < 15° AND duration ≤ 2s → LOG as transient. IF firer in motion (transitioning stance) → suppress alert, log only. Repeated transients (≥3 in session) → escalate to pattern alert via UC-010 | R3: Visual Only | S3: Weapon orientation vector is fully observable from visual pose estimation. No audio needed.
A4: TRUE | B4: UC-002 | C4: A | D4: Core Safety | E4: Unauthorized Person in Danger Zone | F4: Detects a human figure entering a designated danger zone or downrange area while the (live/simulated) range is in operation. Could be a range worker, lost individual, or animal false positive. | G4: Prevent any person from being in the impact area or danger zone during (live/simulated) fire. | H4: Person detection (human body classifier) + geofenced zone overlay on camera feed + range status integration (hot/cold). Focus on both day and night modes. | I4: 1) Detection confidence score 2) Time from zone entry (seen on camera) to alert (latency) 3) False positive rate (animals, shadows, vegetation) 4) Distance from nearest active firing point | J4: Immediate range-wide ceasefire recommendation with location overlay and camera feed to range control. By default: If no external system integration is needed, it will then route the notification and alert to Accel. | K4: Physical sentries and range guards with binoculars - limited visibility, fatigue, no night capability. | L4: - Animal intrusion triggering false alert - Heat shimmer / mirage causing phantom detections - Authorised range party in zone during brief ceasefire windows - Person partially occluded by terrain | M4: P0 - Critical | N4: Not Started | O4: Unauthorized Person in Danger Zone IF human detected in geofenced danger zone AND range status = HOT → immediate CEASEFIRE RECOMMENDATION to range control. IF confidence < 0.7 → flag for human verification before ceasefire call. IF entity classified as animal → LOG, no ceasefire. IF range status = COLD → LOG as administrative entry, no alert. | P4: UC-006, UC-027 | R4: Visual Only | S4: Human figure detection in a geofenced zone is well-established visual analytics. No audio needed.
A5: TRUE | B5: UC-003 | C5: A | D5: Core Safety | E5: Weapon Left Unattended Detection | F5: Detects a weapon stationary and not associated with any person in proximity - on ground, bench, or firing point with no one nearby - beyond a defined time threshold. | G5: No weapon should ever be left unsecured and unattended on a range. | H5: Weapon-shaped object detection + human proximity check within defined radius + time-based trigger (e.g., 30s with no person within 2m). Focus on both day and night modes. | I5: 1) Time weapon is unattended before detection 2) Distance to nearest person when flagged 3) Location context (firing point vs walkway vs rest area) 4) False positive rate (training props, weapon racks) | J5: Alert to nearest safety officer with weapon location, camera feed, and duration unattended. By default: If no external system integration is needed, it will then route the notification and alert to Accel. | K5: Discovered during physical checks or when someone reports a found weapon. | L5: - Weapons deliberately placed in racks (authorised) - Training props / dummy weapons - Weapon placed down momentarily during drill change - Partial occlusion (under bench, behind bag) | M5: P1 - High | N5: Not Started | O5: Weapon Left Unattended IF weapon detected with no person within 2m radius for > 30s → ALERT to nearest safety officer. IF weapon is in designated rack/storage zone → suppress (authorised placement). IF weapon unattended > 120s anywhere → escalate to URGENT. Reset timer when any person enters 2m radius. | P5: UC-008 | R5: Visual Only | S5: Weapon detection + proximity analysis is fully visual. Time-based logic is system-side.
A6: TRUE | B6: UC-004 | C6: A | D6: Core Safety | E6: Negligent / Accidental Discharge Detection | F6: Detects weapon discharge outside designated firing window or when range status is ceasefire/safe. Must distinguish actual discharge from camera artifacts. | G6: Any unplanned discharge is a serious safety incident requiring immediate investigation. | H6: Muzzle flash detection (1-2 frames) + recoil signature + ACOUSTIC GUNSHOT DETECTION for confirmation. Visual alone insufficient in daylight. Focus on both day and night modes. Necessary to consider audio cue from the live environment - adopt this as one of the primary verification layers. | I6: 1) Detection confidence (visual-only vs audio-confirmed) 2) Exact timestamp and location 3) Range status at time of discharge 4) Direction of discharge relative to safe arc 5) Attribution: which position fired | J6: Immediate alert with multi-modal confirmation. Auto-log incident. Trigger ceasefire if range was supposed to be safe. The placement location of audio receiver in this case is important. Ensure the audio cue received is clear - this case may need to define the sound decibel to gauge the distance apart. By default: If no external system integration is needed, it will then route the notification and alert to Accel. | K6: Reported verbally by safety officers - delayed, sometimes missed in noisy environments. | L6: - Daylight muzzle flash nearly invisible on camera - Blank rounds: flash but no recoil - Reflected light / camera artifact mimics flash - Suppressed weapons: minimal flash and report - Multiple simultaneous discharges | M6: P0 - Critical | N6: Not Started | O6: Negligent / Accidental Discharge IF acoustic gunshot detected AND range status ≠ HOT → CRITICAL ALERT + auto-log incident. IF acoustic detected AND range status = HOT but outside firing window → ALERT. IF visual muzzle flash only (no acoustic confirm) → flag as UNCONFIRMED, request human verification. Always capture ±10s multi-camera footage around event timestamp. | P6: UC-008, UC-026 | R6: Visual + Audio | S6: AUDIO CRITICAL. Muzzle flash often invisible in daylight (1-2 frames). Acoustic gunshot detection provides reliable trigger; video provides attribution.
A7: TRUE | B7: UC-005 | C7: A | D7: Core Safety | E7: Post-Firing Weapon Clearing Verification | F7: After ceasefire, visually monitors each firer performing clearing drill - magazine removal, bolt lock, chamber inspection - flags skipped or incorrect steps. | G7: Verify every weapon is made safe before anyone moves from firing position. | H7: Action sequence recognition: detect magazine removal → bolt manipulation → chamber check → show-clear gesture. Take note for night mode, where it can be dark, IR camera need to be considered. | I7: 1) Clearing steps completed per individual 2) Steps skipped or out of order 3) Time from ceasefire to clearing complete 4) Individuals who walk away without clearing | J7: Checklist overlay per firing position. Flag incomplete clearings before range declared safe. By default: If no external system integration is needed, it will then route the notification and alert to Accel. | K7: Safety officer walks the line - slow, can miss detail with many firers. | L7: - Belt-fed weapons have different clearing sequence - Pistols cleared differently than long arms - Body occludes weapon manipulation from certain angles - Speed of manipulation hard to resolve at standard frame rates | M7: P0 - Critical | N7: Not Started | O7: Post-Firing Weapon Clearing Verification On CEASEFIRE event, initiate per-position monitoring. FOR EACH firer: track clearing sequence [magazine remove → bolt lock → chamber check → show-clear]. IF any step skipped → FLAG position as INCOMPLETE. IF firer leaves position before all steps confirmed → URGENT ALERT. Range not declared SAFE until all positions show COMPLETE. | P7: UC-008, UC-006 | R7: Visual Only | S7: Clearing is a sequence of visible physical actions. Fully observable from visual analytics.
A8: TRUE | B8: UC-006 | C8: A | D8: Core Safety | E8: Personnel Count and Position Reconciliation | F8: Continuously counts and maps all personnel against expected manifest. Detects: missing person, extra person, person in wrong position. | G8: Know where every person on the range is at all times. | H8: Multi-camera person detection + position mapping + manifest comparison. | I8: 1) Count accuracy vs manifest 2) Position accuracy (correct lane/zone) 3) Time to detect discrepancy 4) Resilience to occlusion and grouping | J8: Real-time personnel map in range control. Instant alert on count mismatch or position deviation. By default: If no external system integration is needed, it will then route the notification and alert to Accel. | K8: Manual headcount at start and end of serials - no continuous tracking. | L8: - Identical uniforms and gear - Clustering makes count difficult - Camera blind spots - People entering/exiting buildings or vehicles | M8: P0 - Critical | N8: Not Started | O8: Personnel Count and Position Reconciliation On exercise start, lock manifest count. Continuous count at 5s intervals. IF count < manifest → MISSING PERSON alert (P0). IF count > manifest → EXTRA PERSON alert. IF individual deviates > 10m from assigned position → POSITION DEVIATION warning. Reconcile against UC-035 entry/exit log for discrepancy resolution. | P8: UC-045, UC-035 | R8: Visual Only | S8: Person detection and counting is mature visual analytics. Foundation use case for many others.
A9: TRUE | B9: UC-007 | C9: A | D9: Core Safety | E9: Firing Line Breach Detection | F9: Detects when any person moves forward of the firing line during live-fire serial. Even partial step counts. | G9: No person forward of the firing line while weapons are firing. | H9: Person detection + firing line boundary definition in camera frame. Track foot position relative to line. | I9: 1) Detection latency from breach to alert 2) Severity: partial step vs full breach 3) Distance forward of line 4) False positive rate from parallax | J9: Immediate alert. Automatic ceasefire recommendation if breach exceeds threshold. By default: If no external system integration is needed, it will then route the notification and alert to Accel. | K9: Range safety officer watches - can miss peripheral breaches. | L9: - Firing line not physically marked (field firing) - Camera angle makes position ambiguous - Person drops object forward and reaches - Line changes between serials | M9: P0 - Critical | N9: Not Started | O9: Firing Line Breach Detection IF any person's foot position crosses firing line boundary AND range status = HOT → IMMEDIATE ALERT + ceasefire recommendation. IF breach < 0.5m and < 1s (momentary lean) → LOG as minor, no ceasefire. IF breach > 1m or sustained > 2s → CRITICAL, auto-recommend ceasefire. Update line boundary definition at each serial change. | P9: UC-006 | R9: Visual Only | S9: Line boundary + person position is straightforward visual detection.
A10: TRUE | B10: UC-008 | C10: A | D10: Core Safety | E10: Weapon Readiness State Classification | F10: Classifies observable weapon state: holstered/slung, low-ready, high-ready, aimed/shouldered, firing. Feeds into other use cases. | G10: Continuous awareness of weapon states across the range. | H10: Weapon detection + pose classification. Multi-class: slung, low-ready, high-ready, aimed, firing. | I10: 1) Classification accuracy per state 2) State transition detection speed 3) Accuracy across weapon types 4) Robustness to occlusion from gear | J10: Real-time weapon state overlay. Anomaly detection: aimed during ceasefire, firing outside window. | K10: No automated tracking - entirely dependent on safety officer observation. | L10: - Weapon partially hidden by body armour - Pistol states subtler than rifle - Slung weapon bouncing mimics state change - Night/IR conditions alter appearance | M10: P1 - High | N10: Not Started | O10: Weapon Readiness State Classification Continuous classification per tracked individual: SLUNG → LOW-READY → HIGH-READY → AIMED → FIRING. IF state = AIMED and range status ≠ HOT → ALERT. IF state = AIMED and firer not at designated firing position → ALERT. Feed state data to UC-001 (muzzle direction uses weapon state as input) and UC-004 (firing state outside window). | P10: UC-001, UC-004, UC-005 | R10: Visual Only | S10: Weapon state is defined by visible physical configuration. Visual pose classification task.
A11: TRUE | B11: UC-009 | C11: A | D11: Core Safety | E11: Medical Casualty Detection During Live Exercise | F11: Detects person falling, collapsing, or exhibiting distress postures while weapons are in play. Must distinguish genuine event from tactical movement. | G11: Get medical help immediately, even when live fire creates access challenges. Especially critical when the casualty personnel is alone - often overlooked. | H11: Fall detection (sudden vertical-to-horizontal) + stationary posture duration + context analysis. | I11: 1) Time from collapse to detection 2) False positive rate (going prone intentionally vs fall) 3) Distinguishing tactical prone from distress 4) Context: expected vs unexpected posture for exercise phase | J11: Immediate alert to safety officer and medical team. Ceasefire recommendation for affected lane. By default: If no external system integration is needed, it will then route the notification and alert to Accel. | K11: Buddy or adjacent firer notices - delayed, sometimes missed during intense firing. | L11: - Going prone is normal firing position - Simulated casualties in training - Person resting between serials - Gradual event (heat exhaustion) vs sudden collapse | M11: P0 - Critical | N11: Not Started | O11: Medical Casualty Detection IF sudden vertical-to-horizontal transition detected AND person remains stationary > 10s AND context ≠ expected prone position → MEDICAL ALERT to safety officer + medical team. IF audio detects 'man down' call → bypass 10s wait, alert immediately. IF exercise phase expects prone firing → raise stationary threshold to 30s. Always recommend lane-specific ceasefire, not range-wide. | P11: UC-006, UC-004 | R11: Visual-Primary, Audio-Enhanced | S11: VISUAL-PRIMARY: Fall and posture detection are visual. AUDIO-ENHANCED: 'Man down' calls and sudden silence provide secondary confirmation.
A12: TRUE | B12: UC-010 | C12: A | D12: Core Safety | E12: Unsafe Weapon Handling Behaviour Pattern Detection | F12: Identifies accumulated patterns of unsafe behaviour over time - repeated muzzle sweeps, finger on trigger while not firing, weapon manipulation during briefings. Trend indicates intervention needed. | G12: Identify individuals developing unsafe habits before an incident occurs. | H12: Aggregation of detections from UC-001, UC-008, UC-005 over time per individual. Statistical pattern analysis. | I12: 1) Minor violations per individual per session 2) Trend over multiple sessions 3) Correlation between patterns and incident proximity 4) False pattern rate | J12: Flagged report to safety officer with evidence. Recommendation for remedial training. By default: If no external system integration is needed, it will then route the notification and alert to Accel. | K12: Anecdotal - no systematic tracking. | L12: - New trainees expected to have more violations - Cultural differences between units - Pattern window: how far back to look? - Privacy/fairness concerns | M12: P2 - Medium | N12: Not Started | O12: Unsafe Weapon Handling Behaviour Pattern Aggregate violations from UC-001, UC-005, UC-008 per individual per session. IF minor violations ≥ 3 in single session → INTERVENTION ADVISORY to safety officer. IF violations trending upward across sessions (≥2 consecutive sessions above baseline) → REMEDIAL TRAINING recommendation. Weight recent violations higher. Exclude first-session trainees from trend analysis (learning curve allowance). | P12: UC-001, UC-008, UC-005 | R12: Visual Only | S12: Meta-analysis of visual detections aggregated over time. No audio needed.
B13: GROUP B: VEHICLE & MOUNTED SYSTEMS
A14: FALSE | B14: UC-011 | C14: B | D14: Vehicle & Mounted Systems | E14: Vehicle Turret Orientation Safety Monitoring | F14: Tracks turret/gun barrel direction and detects traversal into restricted arc - toward friendly positions, infrastructure, or adjacent lanes. | G14: Vehicle-mounted weapons engage at greater range - unsafe arcs have larger consequences. | H14: Vehicle detection + turret/barrel angle estimation relative to vehicle heading + safe arc overlay based on position. | I14: 1) Turret angle accuracy 2) Time in restricted arc 3) Alert latency 4) Accuracy across vehicle types | J14: Alert to vehicle crew and range control. Turret orientation overlay on range map. | K14: External safety officer from observation tower - limited angle, fatigue. | L14: - Turret sweeps restricted arc during target acquisition - Moving vehicle changes safe arcs continuously - Dust/smoke obscures turret - Multiple vehicles with overlapping arcs | M14: P0 - Critical | N14: Not Started | P14: UC-012 | R14: Visual Only | S14: Turret/barrel orientation is a clearly visible geometric feature. Fully visual.
A15: FALSE | B15: UC-012 | C15: B | D15: Vehicle & Mounted Systems | E15: Vehicle Breach of Designated Movement Corridor | F15: Detects vehicle deviation from designated route or lane. Vehicles straying risk entering impact areas or other active lanes. | G15: Vehicles move fast and take longer to stop - early deviation detection is critical. | H15: Vehicle detection + tracking + geofenced corridor overlay. | I15: 1) Distance of deviation 2) Speed at deviation 3) Duration outside corridor 4) Direction (toward impact area = higher severity) | J15: Alert to vehicle crew and range control with predicted path. | K15: Observation tower spots deviation and radios - often after significant deviation. | L15: - Curves cause natural swing wide - Dust cloud obscures position - Multiple vehicles - which deviated? - Corridor not physically marked | M15: P0 - Critical | N15: Not Started | P15: UC-011, UC-015 | R15: Visual Only | S15: Vehicle tracking against geofenced boundaries is standard visual analytics.
A16: FALSE | B16: UC-013 | C16: B | D16: Vehicle & Mounted Systems | E16: Crew Exposure During Vehicle Live-Fire | F16: Detects personnel with body parts exposed from hatches during vehicle weapon firing when crew should be buttoned up. | G16: Exposed crew during vehicle firing risk injury from blast, casings, or return fire. | H16: Human presence detection at hatch positions during firing events. Classify: closed, partially open, head exposed, torso exposed. | I16: 1) Exposure classification accuracy 2) Correlation with firing events 3) False positives from hatch-mounted equipment 4) Detection at range | J16: Alert to vehicle commander and range control. | K16: External safety staff from distance - very difficult to see hatch status from towers. | L16: - Commander legitimately observing between serials - Hatch open for ventilation, no person exposed - Camera can't see far-side hatches - Vehicle at distance reduces resolution | M16: P1 - High | N16: Not Started | P16: UC-011, UC-004 | R16: Visual Only | S16: Human body detection at hatch openings is visual.
A17: FALSE | B17: UC-014 | C17: B | D17: Vehicle & Mounted Systems | E17: Vehicle-Dismount Safety Proximity Detection | F17: Monitors proximity of dismounted personnel to vehicles during combined arms exercises. Detects soldiers within vehicle danger zones. | G17: Personnel near vehicles during live-fire or maneuver are at risk from blast, movement, and turret rotation. | H17: Person detection + vehicle detection + proximity measurement + danger zone modeling. | I17: 1) Minimum person-vehicle distance 2) Time in danger zone 3) Context: vehicle stationary vs moving, firing vs not 4) Alert response time | J17: Alert to vehicle crew and dismounted personnel via safety officer. | K17: Verbal safety briefs and buddy checks - relies on individual awareness. | L17: - Designated mount/dismount points require proximity - Infantry using vehicle as cover - Vehicle reversing into dismounted position - Danger zone changes with turret rotation | M17: P1 - High | N17: Not Started | P17: UC-006, UC-011 | R17: Visual Only | S17: Person-vehicle proximity is spatial measurement from visual detection.
A18: FALSE | B18: UC-015 | C18: B | D18: Vehicle & Mounted Systems | E18: Vehicle Speed Estimation on Range Roads | F18: Estimates vehicle speed from video and flags speed limit exceedances. Speeding is a common cause of non-combat training injuries. | G18: Enforce speed limits on range roads to prevent vehicle accidents. | H18: Vehicle tracking + calibrated camera geometry + speed from displacement over time. | I18: 1) Speed estimation accuracy (±km/h) 2) False positive rate from parallax 3) Consistency across camera angles 4) Performance in poor visibility | J18: Speed alert to range control. Logged for pattern analysis. | K18: Occasional speed gun checks - infrequent, not continuous. | L18: - Oblique angles distort distance estimation - Dust trail obscures vehicle centroid - Convoy vehicles close together confuse tracking - Calibration drift from camera movement | M18: P2 - Medium | N18: Not Started | P18: UC-012 | R18: Visual Only | S18: Speed estimation from calibrated video is mature visual analytics.
B19: GROUP C: FORMATION & GROUP BEHAVIOUR
A20: TRUE | B20: UC-016 | C20: C | D20: Formation & Group Behaviour | E20: Assault Formation Spacing Violation | F20: Monitors spacing between individuals in tactical formations. Flags when spacing falls outside prescribed standards - too tight or too spread. | G20: Correct spacing is both tactical skill and safety requirement during live-fire movement. | H20: Multi-person detection + inter-person distance measurement + exercise-defined standards. | I20: 1) Average spacing vs standard 2) Min/max deviations 3) Duration of violations 4) Consistently non-compliant individuals | J20: Training feedback spacing heatmap. Real-time alert only if spacing creates safety risk. | K20: Instructor observation - subjective, can only watch part of formation. | L20: - Terrain forces temporary spacing changes - Formation type changes mid-exercise - Smoke/dust reduces visibility - Overlapping personnel from camera angle | M20: P2 - Medium | N20: Not Started | P20: UC-006 | R20: Visual Only | S20: Inter-person distance measurement is straightforward visual analytics.
A21: TRUE | B21: UC-018 | C21: C | D21: Formation & Group Behaviour | E21: Group Bunching Detection at Chokepoints | F21: Detects too many personnel clustering in confined area - doorways, corridors, breach points. Creates tactical failure and real safety risk. | G21: Clustered personnel are vulnerable and create weapon safety risks in confined spaces. | H21: Person density measurement in defined chokepoint zones. Threshold based on zone dimensions and exercise type. | I21: 1) Person count in zone vs maximum 2) Duration of bunching 3) Location frequency (which chokepoints) 4) Correlation with exercise phase | J21: Alert to exercise controller. Training feedback for AAR. | K21: Instructor from outside building - no visibility into chokepoints. | L21: - Controlled stack formation before entry is intentional - Brief transit vs lingering - Camera placement in narrow spaces - Low indoor light | M21: P2 - Medium | N21: Not Started | P21: UC-006, UC-021 | R21: Visual Only | S21: Density counting in a defined zone is visual.
A22: FALSE | B22: UC-019 | C22: C | D22: Formation & Group Behaviour | E22: Friendly Force Crossing Into Opposing Force Zone | F22: In force-on-force exercises, tracks two forces and detects boundary violations - individual from one force enters opposing zone unexpectedly. | G22: Boundary violations can lead to unplanned close-range engagements. | H22: Force identification via visual markers (armbands, helmet bands, IR markers) + zone overlay + crossing detection. | I22: 1) Force marker detection accuracy 2) Boundary crossing frequency 3) Depth of penetration 4) Speed of crossing | J22: Alert to exercise controller and safety staff. Potential exercise pause. | K22: Umpires at boundaries - limited coverage. | L22: - Markers become dirty/obscured - Prisoners or role-players crossing legitimately - Boundary is tactical, not physical - Night exercises: visual markers not visible (need IR) | M22: P1 - High | N22: Not Started | P22: UC-006, UC-043 | R22: Visual Only | S22: Force identification via visual markers and zone detection are visual. IR markers still visual spectrum.
A23: FALSE | B23: UC-020 | C23: C | D23: Formation & Group Behaviour | E23: Observer/Visitor Proximity to Active Exercise | F23: Monitors designated observers, VIPs, or media who must stay in observation areas. Detects drift toward active areas. | G23: Non-participants lack tactical training to understand when they're in danger. | H23: Person detection in observation area + drift tracking. Observers may wear high-vis markers. | I23: 1) Distance from observation boundary 2) Drift speed and direction 3) Time outside designated area 4) Correlation with exercise intensity | J23: Alert to escort / safety officer. | K23: Assigned escort watches - can be distracted with large groups. | L23: - Authorised movement to different observation point - Observer stepping out for phone call - Media with telephoto lenses seeking angles - VIPs who outrank escort and insist on moving closer | M23: P1 - High | N23: Not Started | P23: UC-006, UC-002 | R23: Visual Only | S23: Person tracking in/near zones is standard visual analytics.
B24: GROUP D: URBAN OPERATIONS (MOUT)
A25: FALSE | B25: UC-021 | C25: D | D25: Urban Operations (MOUT) | E25: Room Clearing Sequence Deviation Detection | F25: Tracks movement sequence within rooms during clearing. Flags deviations: missed corners, back-turning to uncleared areas, bunching at doorway. | G25: Correct room clearing is both survival skill and safety requirement with live/blank rounds. | H25: Multi-person indoor tracking + movement vector analysis within room geometry vs expected sequence. | I25: 1) Sequence completion percentage 2) Steps skipped or out of order 3) Time per room vs standard 4) Specific deviations by type | J25: Post-exercise training feedback room-by-room. Real-time alert for safety-critical deviations only. | K25: Instructor from hallway - limited angle, one room at a time. | L25: - Room layouts vary (furniture, obstacles) - Dynamic situations require sequence adaptation - Smoke/flashbang effects obscure camera - Low indoor lighting | M25: P2 - Medium | N25: Not Started | P25: UC-006, UC-018 | R25: Visual-Primary, Audio-Enhanced | S25: VISUAL-PRIMARY: Movement and sequence are visual. AUDIO-ENHANCED: Verbal callouts ('clear left', 'room clear') are integral to the drill.
A26: FALSE | B26: UC-023 | C26: D | D26: Urban Operations (MOUT) | E26: Weapon Discharge in Non-Authorized MOUT Zone | F26: Detects firing activity in rooms/floors designated as no-fire zones - role-player areas, structural damage risk areas. | G26: No-fire zones protect role-players and infrastructure. Any discharge is a serious safety failure. | H26: Muzzle flash detection (more visible indoors) + ACOUSTIC GUNSHOT DETECTION essential for blank rounds. | I26: 1) Detection confidence (visual vs acoustic vs confirmed) 2) Location within building (room-level) 3) Correlation with exercise phase 4) Attribution if possible | J26: Immediate exercise halt for affected building. | K26: Role-players report hearing shots - delayed, sometimes inaccurate. | L26: - Blank rounds: flash but no recoil - hard to detect visually - Indoor echoes complicate acoustic localization - Door slams / simulators mimic gunshots - Flashbang flash vs weapon discharge | M26: P0 - Critical | N26: Not Started | P26: UC-004, UC-025 | R26: Visual + Audio | S26: AUDIO ESSENTIAL indoors. Blank rounds produce minimal visual signature. Acoustic detection reliably captures the report.
A27: TRUE | B27: UC-024 | C27: D | D27: Urban Operations (MOUT) | E27: Stairwell and Elevation Transition Safety Monitoring | F27: Monitors personnel moving between floors with weapons - unsafe muzzle direction, trips/falls, formation breakdowns in vertical transitions. | G27: Stairwells are high-risk for accidental muzzle sweeps and falls with loaded weapons. | H27: Indoor person tracking + weapon orientation estimation in constrained vertical space. | I27: 1) Muzzle violations during stairwell movement 2) Falls or stumbles 3) Formation spacing on stairs 4) Camera coverage quality | J27: Alert for muzzle violations. Training feedback. Safety alert for falls. | K27: No monitoring - stairwells typically unobserved. | L27: - Severe occlusion from tight angles - Weapon position changes rapidly - Low/variable lighting - Brief transit time | M27: P1 - High | N27: Not Started | P27: UC-001, UC-006 | R27: Visual Only | S27: Muzzle direction and fall detection are visual. Challenging camera placement but detection itself needs no audio.
A28: FALSE | B28: UC-025 | C28: D | D28: Urban Operations (MOUT) | E28: Non-Combatant / Role-Player Safety in MOUT | F28: Tracks role-players (civilians, hostages) and monitors proximity to weapon activity. Detects engagement toward role-players or role-players leaving safe positions. | G28: Role-players are real people in a live/blank-fire environment - safety is paramount. | H28: Role-player identification via visual markers + proximity tracking to weapon activity + engagement direction detection. | I28: 1) Min distance between role-player and weapon activity 2) Engagement vectors crossing role-player positions 3) Role-player position stability 4) Time in unplanned proximity | J28: Immediate alert if engagement directed near role-player. Exercise pause if role-player moves to danger. | K28: Role-player self-reports feeling unsafe - after the fact. | L28: - Markers become obscured - Role-player panics and moves unpredictably - Scenario requires role-player near the action - Distinguishing 'near' vs 'at' engagement | M28: P0 - Critical | N28: Not Started | P28: UC-006, UC-001, UC-004 | R28: Visual-Primary, Audio-Enhanced | S28: VISUAL-PRIMARY: Role-player tracking via markers is visual. AUDIO-ENHANCED: Gunshot detection confirms blank fire near role-players.
B29: GROUP E: ENVIRONMENT & INFRASTRUCTURE
A30: FALSE | B30: UC-026 | C30: E | D30: Environment & Infrastructure | E30: Range Flag/Signal Status Detection | F30: Reads visual status of range flags, signal lights, indicator boards and cross-references against range control system. Detects mismatches. | G30: Mismatch between declared status and physical indicators means someone acts on wrong information. | H30: Colour/state classification of flags and lights + range control system data comparison. | I30: 1) Classification accuracy 2) Mismatch detection latency 3) False positives from lighting conditions 4) All flag positions covered by cameras | J30: Immediate alert showing which indicator mismatches. Block status changes until visual confirmation. | K30: Range control declares status and trusts flags are changed - no verification. | L30: - Faded/dirty flags shift colour - Backlighting makes colour ambiguous - Wind wraps flag around pole - Signal lights malfunction | M30: P1 - High | N30: Not Started | P30: UC-004, UC-002 | R30: Visual Only | S30: Colour classification of fixed objects is basic visual analytics.
A31: FALSE | B31: UC-027 | C31: E | D31: Environment & Infrastructure | E31: Downrange Intrusion Detection (Non-Exercise) | F31: Outside active exercise windows, monitors for human, vehicle, or animal activity in impact areas and danger zones. | G31: Impact areas contain UXO and are dangerous even when no firing occurs. | H31: Person/vehicle/animal detection in geofenced zones during non-active periods. 24/7 including IR/thermal. | I31: 1) Detection rate by entity type 2) False positive rate (wildlife) 3) Human vs animal classification accuracy 4) Night/low-light performance | J31: Alert to range control and security. Graduated: animal=log, human=investigate, vehicle=urgent. | K31: Periodic foot patrols and closure signs - large areas, infrequent coverage. | L31: - Wildlife triggers - Heat shimmer phantoms - Authorised maintenance not logged - Terrain obscures ground-level movement | M31: P1 - High | N31: Not Started | P31: UC-002, UC-039 | R31: Visual Only | S31: Perimeter intrusion detection from video is mature. IR/thermal extends to night.
A32: FALSE | B32: UC-028 | C32: E | D32: Environment & Infrastructure | E32: Weather/Visibility Degradation Detection | F32: Monitors visibility from camera feeds - fog, dust, smoke, rain. Flags when visibility drops below exercise threshold. | G32: Reduced visibility changes the safety calculus for different exercise types. | H32: Image quality metrics: contrast ratio, edge detection, visibility distance from known reference points. | I32: 1) Visibility distance accuracy 2) Degradation trend 3) Type (fog vs dust vs smoke) 4) Per-camera status (may be localised) | J32: Alert to range control with assessment. Recommendation to pause/modify if below threshold. | K32: Subjective officer assessment - no objective measurement. | L32: - Localised dust vs general fog - Temporary pyro smoke vs persistent weather - Lens contamination mimics fog - Sun glare mistaken for haze | M32: P2 - Medium | N32: Not Started | P32: UC-043, UC-040 | R32: Visual Only | S32: Visibility assessment from image analysis is well-established.
A33: FALSE | B33: UC-029 | C33: E | D33: Environment & Infrastructure | E33: Target Area Condition Monitoring | F33: Monitors target arrays - detecting fallen, destroyed, moved, or obscured targets. Flags when state doesn't match expected configuration. | G33: Wrong target state means firers may engage wrong area or not engage - safety risk. | H33: Target detection + state classification (up/down/damaged/missing) + comparison against expected config. | I33: 1) State classification accuracy 2) Latency from change to detection 3) Coverage of target area 4) False positives from targets hit during firing (expected) | J33: Alert showing which targets need attention. Pre-exercise verification. | K33: Physical check by target operators - requires ceasefire and personnel downrange. | L33: - Targets hit and falling is expected - Wind-blown vs shot targets - Partial damage (leaning) - Electronic pop-up targets - must track intended state | M33: P2 - Medium | N33: Not Started | P33: UC-026 | R33: Visual Only | S33: Target detection and state classification are visual.
B34: GROUP F: PRE-EXERCISE & ADMINISTRATIVE
A35: TRUE | B35: UC-031 | C35: F | D35: Pre-Exercise & Administrative | E35: PPE Compliance Detection | F35: Verifies all personnel on firing line wearing required PPE - ear protection, eye protection, helmet, body armour. | G35: PPE prevents non-combat injuries from noise, debris, and ricochet. | H35: Object detection on person: ear muffs, eyewear, helmet, body armour. | I35: 1) Detection accuracy per PPE type 2) Known limitations (ear plugs invisible) 3) False positives (sunglasses vs ballistic eyewear) 4) Verified before firing commences | J35: Alert listing non-compliant personnel and missing PPE. | K35: Visual check by safety officer - can miss items with many firers. | L35: - Ear plugs nearly invisible - Ballistic eyewear vs sunglasses - PPE worn improperly (helmet unbuckled, eyewear on forehead) - Body armour under uniform is invisible | M35: P1 - High | N35: Not Started | P35: UC-006 | R35: Visual Only | S35: PPE with distinct silhouettes is visually detectable. Known limitation: ear plugs and concealed items.
A36: TRUE | B36: UC-032 | C36: F | D36: Pre-Exercise & Administrative | E36: Range Briefing Attendance Verification | F36: Headcount and presence verification during mandatory safety briefings. Detects late arrivals, early departures, absentees. | G36: All firers must attend brief - anyone firing without attending is a safety risk. | H36: Person counting in briefing area + duration tracking + manifest comparison. | I36: 1) Headcount accuracy vs manifest 2) Attendance duration per individual 3) Late arrival detection 4) Early departure detection | J36: Attendance log with timestamps. Alert for discrepancies before firing. | K36: Sign-in sheet - easily gamed, no duration verification. | L36: - People at back of briefing area - Open area vs confined room - Brief toilet break and return - Multiple briefings for different serials | M36: P2 - Medium | N36: Not Started | P36: UC-006, UC-035 | R36: Visual Only | S36: Headcount and presence tracking are standard visual analytics.
A37: FALSE | B37: UC-033 | C37: F | D37: Pre-Exercise & Administrative | E37: Weapon Assembly/Disassembly Area Monitoring | F37: Monitors weapon preparation areas for unsafe practices: muzzle violations during assembly, pointing at others, loading in non-designated areas. | G37: Preparation areas are where distracted handling mistakes happen most. | H37: Weapon detection + muzzle direction tracking + activity zone enforcement. | I37: 1) Muzzle violations in preparation area 2) Loading outside designated zone 3) Violation rate comparison between units 4) Time-of-day patterns (fatigue) | J37: Alert to safety supervisor. Unit performance feedback. | K37: Occasional safety officer walk-through - snapshot, not continuous. | L37: - Disassembly means muzzle direction ambiguous - Cleaning involves pointing in various directions - Crowded and occluded areas - Training vs live weapons look identical | M37: P2 - Medium | N37: Not Started | P37: UC-001, UC-008 | R37: Visual Only | S37: Muzzle direction and zone detection are visual analytics.
A38: FALSE | B38: UC-034 | C38: F | D38: Pre-Exercise & Administrative | E38: Ammunition Handling Area Safety Monitoring | F38: Monitors ammunition points for unsafe handling: dropping, incorrect container handling, unauthorised personnel. | G38: Ammunition handling errors can cause injury or loss. | H38: Activity recognition in ammo area + person authorization + handling anomaly detection. | I38: 1) Unauthorised person detections 2) Dropping/mishandling events 3) Container exposure duration 4) Personnel count vs authorised | J38: Alert to ammunition NCO and safety officer. | K38: Ammunition NCO supervises - single point of failure. | L38: - Authorised vs unauthorised personnel distinction - Dropping vs setting down firmly - Ammunition in pockets (invisible) - Temporary field ammo points (no fixed camera) | M38: P2 - Medium | N38: Not Started | P38: UC-006, UC-035 | R38: Visual Only | S38: Activity recognition and zone-based tracking are visual.
A39: TRUE | B39: UC-035 | C39: F | D39: Pre-Exercise & Administrative | E39: Range Access Point Entry/Exit Logging | F39: Logs every person and vehicle entering/exiting. Detects tailgating, non-stopping vehicles, reverse-direction movement. | G39: Accurate entry/exit logging is foundation for knowing who is on the range. | H39: Person/vehicle detection at access points + direction + counting + tailgate detection. | I39: 1) Count accuracy (entry vs exit balance) 2) Tailgate detection rate 3) Vehicle stop compliance 4) Reverse direction alerts | J39: Automatic access log with timestamps and captures. Anomaly alerts. | K39: Guard manually logs - errors, missed entries, illegible records. | L39: - Pedestrians and vehicles at same point - Legitimate convoys vs tailgating - Emergency vehicles bypassing procedure - Poor lighting or weather | M39: P1 - High | N39: Not Started | P39: UC-006, UC-039 | R39: Visual Only | S39: Counting and direction detection at fixed points are mature visual analytics.
B40: GROUP G: POST-EXERCISE & INCIDENT SUPPORT
A41: TRUE | B41: UC-036 | C41: G | D41: Post-Exercise & Incident Support | E41: Post-Exercise Range Sweep Personnel Tracking | F41: Tracks sweep team coverage after firing. Verifies all required zones walked. Flags gaps before range declared safe. | G41: Incomplete sweep may leave casualty, UXO, or hazard undetected. | H41: Person tracking + path mapping + coverage overlay against required zones. | I41: 1) Zone coverage percentage 2) Coverage gaps 3) Time per zone (too fast = superficial) 4) Sweep team count sufficient | J41: Coverage map for range officer. Range not safe until 100% covered. | K41: Self-reported completion - no thoroughness verification. | L41: - Terrain prevents straight-line sweep - Team splits up - Camera coverage gaps at range edges - Night conditions | M41: P1 - High | N41: Not Started | P41: UC-006, UC-045 | R41: Visual Only | S41: Person tracking and path mapping are visual analytics.
A42: TRUE | B42: UC-037 | C42: G | D42: Post-Exercise & Incident Support | E42: Incident Replay and Timeline Reconstruction | F42: After safety incident, auto-identifies relevant camera feeds, synchronises them, generates multi-angle timeline. | G42: Accurate reconstruction prevents recurrence and supports investigations. | H42: Multi-camera sync + event timestamp anchoring + clip extraction + AUDIO TRACK SYNC for complete picture. | I42: 1) Time from incident to replay available 2) Camera angles included 3) Timeline accuracy (frame-level) 4) Completeness of capture | J42: Multi-angle synchronised replay within minutes of incident report. | K42: Manual CCTV review - hours searching unsynchronised feeds. | L42: - Different frame rates across cameras - Clock sync issues - Relevant camera obstructed - Incident spans multiple areas | M42: P1 - High | N42: Not Started | P42: UC-004, UC-009, UC-045 | R42: Visual + Audio | S42: AUDIO VALUABLE. Visual provides spatial picture; audio provides timeline anchoring - gunshot timing, verbal commands, radio calls, and contextual sound.
A43: FALSE | B43: UC-038 | C43: G | D43: Post-Exercise & Incident Support | E43: Spent Brass / Debris Detection in Safety Lanes | F43: Detects accumulation of spent casings and debris in walkways that could cause slips or trips. | G43: Brass underfoot is a real slip hazard, especially indoor ranges with concrete floors. | H43: Small object accumulation detection with high-res cameras. Density estimation in walkway zones. | I43: 1) Accumulation detection accuracy 2) Density threshold calibration 3) False positives from other small objects 4) Camera resolution requirements | J43: Alert to maintenance. Trend data on accumulation rates. | K43: Visual check during breaks - often missed until someone slips. | L43: - Individual casings too small for standard cameras - Brass colour blends with sandy surfaces - Density pattern vs individual casing detection - Indoor vs outdoor contrast | M43: P3 - Low | N43: Not Started | R43: Visual Only | S43: Debris accumulation is visual, requiring higher resolution cameras.
A44: FALSE | B44: UC-039 | C44: G | D44: Post-Exercise & Incident Support | E44: Unauthorized After-Hours Range Activity | F44: Monitors range outside scheduled hours. Any detected activity triggers alert. | G44: After-hours activity is either unauthorized training (dangerous) or criminal. | H44: Person/vehicle detection in IR/thermal during non-active hours. Any detection = alert. | I44: 1) Low-light detection rate 2) False positive rate (animals) 3) Thermal classification accuracy 4) Security notification speed | J44: Alert to security with feed, location, classification. | K44: Perimeter fence and periodic patrols - large area, infrequent. | L44: - Wildlife common on military ranges - Overnight maintenance not logged - Residual heat from vehicles vs active - Weather causing false motion triggers | M44: P1 - High | N44: Not Started | P44: UC-027, UC-035 | R44: Visual Only | S44: Perimeter surveillance is core visual analytics. IR/thermal covers night.
A45: FALSE | B45: UC-040 | C45: G | D45: Post-Exercise & Incident Support | E45: Fire and Smoke Detection from Range Activity | F45: Detects fires started by tracer rounds, pyrotechnics, or ricochets. Critical in dry conditions. | G45: Range fires endanger personnel, destroy infrastructure, cause environmental damage. | H45: Smoke detection (plume shape, colour, movement) + flame detection (colour, flicker) + growth tracking. | I45: 1) Detection time from ignition 2) False positives (dust, exhaust, pyro effects) 3) Growth rate estimation 4) Location accuracy for response dispatch | J45: Immediate alert to range control and fire response with location and size estimate. | K45: Observation tower - limited during exercises when attention is on safety. | L45: - Intentional pyrotechnics vs unintended fire - Controlled burns on adjacent land - Vehicle dust mimicking smoke - Small smouldering with minimal visible smoke | M45: P1 - High | N45: Not Started | P45: UC-028 | R45: Visual Only | S45: Fire and smoke detection from video is mature, commercially available technology.
B46: GROUP H: ADVANCED / COMPOUND
A47: FALSE | B47: UC-042 | C47: H | D47: Advanced / Compound | E47: Drone/UAS Operational Safety Monitoring | F47: Tracks UAS within range. Detects flight corridor deviations, unsafe altitude over personnel, unauthorized presence over live-fire areas. | G47: UAS near live-fire are both at risk and a risk to personnel. | H47: Small object aerial detection + flight path tracking + geofenced corridor enforcement + ACOUSTIC DRONE DETECTION for small UAS beyond visual range. | I47: 1) Detection range (visual vs acoustic) 2) Flight path deviation 3) Altitude accuracy from ground cameras 4) False positives (birds, debris) | J47: Alert to UAS operator and range control. | K47: UAS operator self-manages - no independent monitoring. | L47: - Small UAS invisible beyond 100-200m - Birds mistaken for drones - Multiple UAS simultaneously - Beyond line-of-sight from cameras | M47: P1 - High | N47: Not Started | P47: UC-006, UC-002 | R47: Visual + Audio | S47: AUDIO VALUABLE. Small UAS (<2kg) extremely hard to detect visually beyond 100-200m. Drone motors have distinct acoustic signatures at greater range. Audio alerts; visual confirms.
A48: FALSE | B48: UC-043 | C48: H | D48: Advanced / Compound | E48: Night Exercise Safety Monitoring (IR/Thermal) | F48: Operates in IR/thermal for night exercises. Same safety rules apply but analytics use thermal signatures. | G48: Safety standards don't change at night - detection capability must persist. | H48: Thermal person detection + weapon detection in IR + muzzle flash detection (highly visible at night) + standard zone analytics on thermal feeds. | I48: 1) Accuracy vs daylight equivalents 2) Person count in thermal 3) Weapon state classification in IR 4) Muzzle flash sensitivity (should be higher) | J48: Same alert framework as daytime. Highlight any degraded capabilities. | K48: Night safety officers with NVDs - limited FOV, fatigue-prone. | L48: - Vehicle/weapon heat signatures persist after use - Personnel blend thermally when close - Environmental heat sources - Rain reduces thermal contrast | M48: P1 - High | N48: Not Started | P48: UC-001 through UC-010 | R48: Visual Only | S48: Thermal/IR is still visual analytics in different spectrum. Muzzle flash more detectable at night.
A49: FALSE | B49: UC-044 | C49: H | D49: Advanced / Compound | E49: Pyrotechnics / Grenade Range Safety Monitoring | F49: Monitors grenade/demolition ranges: personnel in blast radius, throwing errors, misfire procedures. | G49: Explosives are the highest consequence weapon on any training range. | H49: Person detection + blast zone geofencing + throw trajectory estimation + ACOUSTIC DETONATION CONFIRMATION. Visual disrupted by explosion. | I49: 1) Personnel position at detonation moment 2) Throw error detection (short, wild) 3) Misfire detection (no detonation in expected time) 4) Camera recovery after flash/smoke 5) Audio detonation confirmation | J49: Alert if personnel in blast zone. Misfire protocol if no detonation. Auto-log every throw. | K49: Safety officer in hardened bay - limited angle, blast impairs observation. | L49: - Flash saturates camera 2-5s - Smoke obscures 10-30s post-detonation - Misfire = absence of expected event - Thrown grenade trajectory hard to track - Bounce-back of grenades | M49: P0 - Critical | N49: Not Started | P49: UC-006, UC-002 | R49: Visual + Audio | S49: AUDIO CRITICAL. Camera flash-blinded at detonation. Acoustic confirmation is definitive. Misfire detection (absence of bang) more reliable via audio.
A50: FALSE | B50: UC-045 | C50: H | D50: Advanced / Compound | E50: Multi-Camera Handoff for Continuous Person Tracking | F50: Maintains identity-agnostic tracking as individuals move across camera zones. Re-acquires and maintains track across handoffs. | G50: Foundation capability enabling all position-dependent use cases across large range. | H50: Appearance-based re-ID + spatial prediction (exit→entry) + temporal correlation. | I50: 1) Handoff success rate 2) Track fragmentation rate 3) Re-ID accuracy with identical uniforms 4) Handoff latency | J50: Continuous track maintained across entire complex. Feeds UC-006 and all position use cases. | K50: No continuous tracking - headcounts at discrete checkpoints only. | L50: - Identical uniforms make re-ID very hard - Variable time gaps between camera zones - Groups entering/exiting together - Appearance changes (putting on/removing gear) | M50: P1 - High | N50: Not Started | P50: UC-006 | R50: Visual Only | S50: Multi-camera tracking and re-identification are visual analytics.
B51: GROUP I: TRAINING QUALITY & PERFORMANCE
A52: TRUE | B52: UC-046 | C52: I | D52: Training Quality & Performance | E52: Shooting Stance and Posture Assessment | F52: Evaluates firer's shooting posture - body position, weapon hold, stance width, lean, stability. Flags unsafe postures and provides training feedback. | G52: Poor posture reduces accuracy and increases risk of losing weapon control. | H52: Pose estimation (body keypoints) + weapon hold classification + stance template comparison. | I52: 1) Posture classification accuracy 2) Deviation from ideal 3) Consistency across shots 4) Correlation with accuracy | J52: Post-exercise feedback per firer. Real-time alert only for unsafe postures. | K52: Instructor observation - subjective, 1-2 firers at a time. | L52: - Body armour alters correct posture - Individual body proportions vary - Recoil absorption changes between shots - Uneven ground differs from flat range | M52: P3 - Low | N52: Not Started | P52: UC-008, UC-001 | R52: Visual Only | S52: Pose estimation and posture classification are core visual analytics.
A53: FALSE | B53: UC-047 | C53: I | D53: Training Quality & Performance | E53: Reaction Time Measurement on Target Exposure | F53: Measures time between target appearing and first engagement. Objective performance data. | G53: Reaction time is key marksmanship metric - objective measurement enables fair assessment. | H53: Target state change detection + firing event detection. ACOUSTIC provides more precise firing timestamp. | I53: 1) Reaction time accuracy (±ms) 2) Sync between target event and firing detection 3) Per-firer consistency 4) Session performance trend | J53: Objective reaction time data per firer per exposure. | K53: Stopwatch or electronic target - only on wired ranges. | L53: - Multiple firers on same target - Position adjustment delay - Electronic vs video timing sync - Suppressed weapons delay audio | M53: P3 - Low | N53: Not Started | P53: UC-008, UC-004 | R53: Visual-Primary, Audio-Enhanced | S53: VISUAL-PRIMARY: Target exposure is visual. AUDIO-ENHANCED: Acoustic shot timing resolves to ms vs ±33ms from video at 30fps.
A54: FALSE | B54: UC-048 | C54: I | D54: Training Quality & Performance | E54: Communication Gesture Recognition | F54: Recognises standard military hand signals - halt, move, enemy spotted, rally, cease fire. Assesses whether recipients responded. | G54: Hand signals are critical tactical skill - video enables objective assessment at scale. | H54: Hand/arm pose recognition + gesture classification + recipient response tracking. | I54: 1) Gesture accuracy per signal type 2) False positives from general arm movement 3) Response correlation 4) Signal clarity assessment | J54: Training feedback on signal quality and team response. | K54: Instructor from one vantage point - misses most signals. | L54: - Signals while moving (distorted) - Unit cultural variations - Partial signals behind cover - Verbal acknowledgment instead of physical | M54: P3 - Low | N54: Not Started | P54: UC-006, UC-016 | R54: Visual-Primary, Audio-Enhanced | S54: VISUAL-PRIMARY: Gesture recognition is visual. AUDIO-ENHANCED: Verbal acknowledgments ('roger', 'moving') complete the communication assessment.
A55: FALSE | B55: UC-049 | C55: I | D55: Training Quality & Performance | E55: Tactical Bound Timing and Coordination Assessment | F55: Tracks fire-and-movement timing - when each person moves, exposure duration, whether covering fire is provided. | G55: Fire-and-movement is fundamental - video can objectively assess coordination. | H55: Multi-person movement tracking + state classification + ACOUSTIC FIRING DETECTION for covering fire confirmation. | I55: 1) Bound timing (exposure per person) 2) Covering fire overlap 3) Pair/team sync quality 4) Movement speed/distance | J55: Coordination assessment per pair/team. Timing diagram for AAR. | K55: Instructor from single point - misses detail, subjective. | L55: - Covering fire with blanks - minimal visual signature - Dead ground movement out of view - Multiple simultaneous pairs - Terrain overrides standard drill | M55: P3 - Low | N55: Not Started | P55: UC-006, UC-016, UC-004 | R55: Visual-Primary, Audio-Enhanced | S55: VISUAL-PRIMARY: Movement tracking is visual. AUDIO-ENHANCED: Detecting covering fire (esp. blank rounds) via audio is far more reliable.
A56: FALSE | B56: UC-050 | C56: I | D56: Training Quality & Performance | E56: After-Action Review Automated Highlight Generation | F56: Auto-identifies and tags key exercise moments: first contact, casualties, decisions, safety violations. Generates multi-angle highlight reel. | G56: AARs are the primary learning mechanism - auto highlights cut prep from hours to minutes. | H56: Event aggregation from all active use cases + significance scoring + multi-camera clip extraction + AUDIO for verbal context. | I56: 1) Highlight relevance accuracy 2) Coverage of significant events 3) Time from exercise end to availability 4) Multi-angle + audio sync quality | J56: Tagged highlight package with multi-angle clips and audio. Browsable by event/time/location. | K56: Manual review and clip extraction - hours of work, inconsistent. | L56: - Defining 'significant' algorithmically - Exercise-specific significance - Privacy of individual performance - Storage/processing requirements | M56: P2 - Medium | N56: Not Started | P56: UC-037, UC-004, UC-009 | R56: Visual + Audio | S56: AUDIO VALUABLE. Visual provides events; verbal commands and radio traffic are essential context for meaningful AAR.
B57: GROUP J: SWT WEAPONS
A58: FALSE | B58: UC-051 | C58: J | D58: SWT Weapons | E58: Weapon Visibility Rule (Consolidated) | F58: Consolidated policy covering all scenarios where a weapon disappears from view within the detection zone. Handles three sub-scenarios based on person count at disappearance: (A) no person present, (B) one person — weapon taken out of frame or occluded, (C) multiple persons present. Merges original Policies 1, 2, and 3. | G58: Ensure any weapon that is no longer visible triggers a timely alert once all associated persons have cleared the detection zone. | H58: Weapon-shaped object classifier loses confirmed detection (absent ≥3 consecutive frames). Person-detection classifier tracks associated individuals in the zone. T1 and T2 timers govern alert timing based on person presence state. | I58: 1) Weapon visibility state (visible / occluded / out-of-frame) 2) Associated person count in detection zone 3) T1 timer state (countdown after zone is clear) 4) T2 timer state (grace period while person remains) 5) Weapon reappearance events (timer reset trigger) | J58: Alert triggered after T1 expires once all associated persons have left and weapon remains unseen. If weapon reappears before T1 expires, all timers reset and no alert is issued. | K58: Manual observation. No automated tracking of weapon visibility state or person-presence changes. | L58: - Weapon occluded by passing non-associated person - Person re-enters zone after T1 has started - Weapon reappears briefly then disappears again (reset-restart cycle) - Multiple persons leaving at different times | M58: P0 - Critical | N58: Draft | O58: IF weapon not visible AND 0 persons → start T1 (Weapon {Weapon_id} Missing) → alert. IF weapon not visible AND 1 person near → start T2 (Weapon {Weapon_id} Occluded by Person {Person_id) → alert. IF weapon not visible AND 1 person far → start T1(Weapon {Weapon_id} Taken by Person {Person_id)) → alert. IF weapon not visible AND 2+ persons → priority rules: ANY person far → T1 (Weapon {Weapon_id} Taken by Person {Person_id)) All 2+ persons near → T2 (Weapon {Weapon_id} Occluded by Person {Person_id)) 1 near, 0 far → T2 (Weapon {Weapon_id} Occluded by Person {Person_id)) All left ROI → T1(Weapon {Weapon_id} Taken by Person {Person_id)) IF weapon reappears before window expiry → reset all timers, no alert. | P58: Need to detect the object first and when a weapon detection disappears, the policy walks every LOCKED person and measures: distance = center_of_person_box → center_of_weapon's_last_known_position Then classifies: • distance ≤ NEAR_DISTANCE_PX (200 px) → 'near' → contributes to near_count • distance > NEAR_DISTANCE_PX (200 px) → 'far' → contributes to far_count • no locked persons in ROI at all → 'none' | Q58: Configuration: "WEAPON_CONFIDENCE_THRESHOLD": 0.80 Minimum YOLO confidence for a weapon detection to count. Lower = more sensitive (more false positives). Higher = miss small/blurry weapons. "PERSON_CONFIDENCE_THRESHOLD": 0.80 Minimum YOLO confidence for a person detection to count. "T1_DURATION_THRESHOLD": 2.0 Seconds to wait before firing an URGENT alert. Used by: Missing, Taken, Boundary Violation (UC-052 uses 0s = immediate). "T2_DURATION_THRESHOLD": 5.0 Seconds to wait before firing a WARNING alert (longer grace period). Used by: Occluded scenarios (person standing near weapon). "NEAR_DISTANCE_PX": 200 THE KEY DISTANCE FOR UC-051. Pixel radius around the weapon's last-known position. Person within this distance = 'near' (occluded → T2). Person beyond this distance = 'far' (taken → T1). | R58: Visual Only | S58: Weapon and person detection are fully visual. No audio input required. | T58: Policy - UC-051
A59: FALSE | B59: UC-052 | C59: J | D59: SWT Weapons | E59: Weapon Boundary Violation (Consolidated) | F59: Consolidated policy for all scenarios where a weapon crosses a restricted zone boundary, regardless of whether a person is carrying it. Person presence is captured as context but does not affect alert timing — alert is always immediate. | G59: Ensure any weapon leaving its authorised zone is immediately flagged — whether carried, thrown, kicked, or otherwise moved across the boundary. | H59: Weapon-shaped object trajectory crosses a defined restricted zone boundary line or polygon edge. Requires weapon tracked inside zone before crossing. Boundary definitions pre-loaded per exercise/zone configuration. | I59: 1) Weapon position relative to zone boundary (inside / crossing / outside) 2) Weapon trajectory vector at crossing 3) Person association status at crossing (context only) 4) Crossing speed and direction 5) Whether weapon returns inside boundary after crossing | J59: Immediate alert the moment weapon crosses the restricted boundary. No grace period, no timer. Alert remains active until operator acknowledges. Highest priority — overrides UC-051 timers if both conditions occur simultaneously. | K59: Manual observation. No automated boundary monitoring or crossing detection. | L59: - Weapon bouncing across boundary and returning (transient crossing) - Camera parallax causing apparent crossing that did not occur - Multiple weapons near boundary simultaneously - Authorised staff repositioning weapon across boundary | M59: P0 - Critical | N59: Draft | O59: IF weapon crosses restricted zone boundary → IMMEDIATE alert (no timer, no delay). Person association is logged as context but does not suppress or delay the alert. Alert remains active until operator acknowledges. HIGHEST PRIORITY — overrides all UC-051 (Visibility) timers if both conditions occur simultaneously. | P59: Zone boundary definitions (pre-loaded per exercise). UC-051 (Weapon Visibility Rule). | R59: Visual Only | S59: Weapon position tracking and boundary crossing detection are fully visual. No audio required. | T59: Policy - UC-052
A60: FALSE | B60: UC-053 | C60: J | D60: SWT Weapons | E60: Cross-Camera Person Re-Identification for Weapon Accountability Under Occlusion | F60: A single base station (training range) is covered by multiple CCTV cameras with non-overlapping or partially overlapping fields of view, each covering one or more lanes (e.g. Lane 1 through Lane 6). Trainees move freely between lanes while carrying their assigned weapons. A naïve weapon-detection model treats every loss of weapon visibility as a loss of the weapon. The moment a trainee picks up and carries a weapon — barrel down, slung, or shielded by the body or carry posture — the weapon is occluded and disappears from detection. A frame-by-frame detector would raise a "weapon missing" alert on every normal carry, generating constant false alarms and destroying operator trust. The accountability question is not "is the weapon visible right now," but "is the weapon still where it should be." | G60: Maintain stable person identity within each station so weapon-association, dwell-time, and movement-tracking analytics (UC-051, UC-052) work continuously even when persons leave one camera view and reappear in another. Without Re-ID, ByteTrack assigns a new track ID every time a person crosses camera boundaries, breaking continuity of all dependent policies. | H60: Alert condition — the only trigger. A tracked, weapon-associated trainee crosses the base-station boundary and the weapon cannot be visually confirmed anywhere in the monitored scene at that moment (neither carried on the person nor set down within the area). Occlusion alone never triggers an alert; lane-to-lane movement never triggers an alert; only an unconfirmed weapon leaving the controlled boundary does. Key distinction. "Occluded" ≠ "missing." Occlusion is a visibility state inside a known containment boundary; missing is an accountability state at the boundary edge. The system holds the weapon's last known association open for as long as the person carrying it remains tracked and inside the boundary, and only escalates when containment can no longer be assumed. | I60: (1) Weapon visible and associated, person inside the base-station boundary → armed, accounted for. (2) Weapon no longer visible (occluded by carry posture), person still tracked inside the boundary → occluded, presumed retained — no alert. Occlusion is the expected condition once a weapon is carried. Movement between lanes (Lane 1 → Lane 6) is normal and never triggers an alert. (3) Weapon-associated person crosses the base-station boundary while the weapon cannot be visually confirmed → accountability warning raised for human verification. | J60: Persistent person identity (re-ID) across all cameras covering the base station. A trainee tracked in Lane 1 must resolve to the same identity when they reappear in Lane 6, despite the camera handoff and any gap in coverage. Weapon-to-person association. While weapon and person are jointly visible, the weapon is bound to that person's identity. Association persistence under occlusion. Once bound, the weapon's status is inferred from the person's continuously tracked state. Loss of weapon visibility does not, on its own, change the weapon's status. | K60: No cross-camera tracking exists. ByteTrack provides per-camera track IDs only. A person crossing from one camera to another currently gets two unrelated IDs. Operator must mentally correlate the same individual across screens. | L60: - Identical uniforms / appearance among multiple persons (military training context) - Heavy occlusion / partial body crops giving weak embeddings - Lighting variation between cameras at the same station - Persons leaving station coverage > TTL and re-entering (gallery expired) - Two stations adjacent — accidental cross-station match (prevented by design) - YOLO26 embed() returns variable feature dim — handled with L2 normalize + first-extraction baseline | M60: P1 - High | N60: Draft | O60: TWO-LAYER: Layer 1 (BoT-SORT): per-camera identity via tracker reid_yaml — set with_reid: True, model: auto Layer 2 (StationReID): every N frames, extract embedding via yolo_model.embed(crop), L2-normalize, compare against station gallery; match if cosine >= REID_MATCH_THRESHOLD (0.65 default); ambiguous if top-2 within margin → defer; new_person if no match; transfer UC-051 locks on identity change. | P60: BoT-SORT (Ultralytics v8.3.114+) with with_reid: True. YOLO26L person detector with embed() endpoint. GPU memory for embedding extraction. UC-051, UC-052 as consumers of person IDs. | R60: Visual Only | S60: Person appearance and inter-camera continuity are fully visual. Re-ID models operate on RGB crops only — no audio input required. | T60: Policy - UC-053
A61: FALSE | B61: UC-054 | R61: Visual Only

Sheet Column Guide
A1: Column Name | B1: Purpose | C1: How to Fill It | D1: Good Example | E1: Bad Example
A2: UC ID | B2: Unique reference | C2: Sequential: UC-001, UC-002 | D2: UC-001 | E2: 'the safety one'
A3: Group | B3: Letter code for group | C3: A through I | D3: A | E3: (blank)
A4: Category | B4: Domain grouping | C4: From group name | D4: Core Safety | E4: Bad stuff
A5: Use Case Name | B5: Scannable label | C5: Short noun phrase | D5: Weapon Muzzle Direction Violation | E5: Safety issue
A6: Description | B6: Full scope + success | C6: What + what does good look like? | D6: Detects muzzle sweep across persons... | E6: Detect bad things
A7: User Intent | B7: The WHY | C7: Underlying goal | D7: Prevent unsafe muzzle orientation | E7: Keep people safe
A8: Trigger / Detection Method | B8: How the system detects it | C8: Visual method, classifiers, thresholds | D8: Pose estimation + weapon vector + person detection | E8: Camera watches
A9: Key Behaviours to Track | B9: Measurable signals | C9: 3-5 log-reviewable items | D9: Muzzle angle, duration, frequency per person | E9: Track if works
A10: Desired Outcome | B10: Target flow | C10: Detection → response | D10: Immediate alert with snapshot and location | E10: Fix it
A11: Current Handling | B11: Baseline | C11: Honest before state | D11: Post-event CCTV review - after the fact | E11: Fine / N/A
A12: Edge Cases | B12: Failure scenarios | C12: 3-5 boundary conditions | D12: Momentary sweep during transition | E12: (blank)
... A19: Policy Sheet | B19: Link to detail | C19: Auto - hyperlink when policy sheet created | D19: → Policy - UC-001 | E19: (blank = not created)

Sheet Modality Summary
A1: Detection Modality | B1: Count | C1: Implication
A2: Visual Only | B2: 34 | C2: Fully achievable with camera systems. No additional sensor infrastructure.
A3: Visual + Audio | B3: 6 | C3: Requires integrated acoustic sensors. Video alone would miss critical events.
A4: Visual-Primary, Audio-Enhanced | B4: 6 | C4: Functions with video alone but audio significantly improves accuracy or completeness.
A5: TOTAL | B5: 46
A7: USE CASES REQUIRING AUDIO INTEGRATION
A8: UC ID | B8: Use Case Name | C8: Why Audio Is Needed
A9: UC-004 | B9: Negligent / Accidental Discharge Detection | C9: AUDIO CRITICAL. Muzzle flash often invisible in daylight (1-2 frames). Acoustic gunshot detection provides reliable trigger; video provides attribution.
A10: UC-009 | B10: Medical Casualty Detection During Live Exercise | C10: VISUAL-PRIMARY: Fall and posture detection are visual. AUDIO-ENHANCED: 'Man down' calls and sudden silence provide secondary confirmation.
A11: UC-021 | B11: Room Clearing Sequence Deviation Detection | C11: VISUAL-PRIMARY: Movement and sequence are visual. AUDIO-ENHANCED: Verbal callouts ('clear left', 'room clear') are integral to the drill.
A12: UC-023 | B12: Weapon Discharge in Non-Authorized MOUT Zone | C12: AUDIO ESSENTIAL indoors. Blank rounds produce minimal visual signature. Acoustic detection reliably captures the report.
A13: UC-025 | B13: Non-Combatant / Role-Player Safety in MOUT | C13: VISUAL-PRIMARY: Role-player tracking via markers is visual. AUDIO-ENHANCED: Gunshot detection confirms blank fire near role-players.
A14: UC-037 | B14: Incident Replay and Timeline Reconstruction | C14: AUDIO VALUABLE. Visual provides spatial picture; audio provides timeline anchoring - gunshot timing, verbal commands, radio calls, and contextual sound.
A15: UC-042 | B15: Drone/UAS Operational Safety Monitoring | C15: AUDIO VALUABLE. Small UAS (<2kg) extremely hard to detect visually beyond 100-200m. Drone motors have distinct acoustic signatures at greater range. Audio alerts; visual confirms.
A16: UC-044 | B16: Pyrotechnics / Grenade Range Safety Monitoring | C16: AUDIO CRITICAL. Camera flash-blinded at detonation. Acoustic confirmation is definitive. Misfire detection (absence of bang) more reliable via audio.
A17: UC-047 | B17: Reaction Time Measurement on Target Exposure | C17: VISUAL-PRIMARY: Target exposure is visual. AUDIO-ENHANCED: Acoustic shot timing resolves to ms vs ±33ms from video at 30fps.
A18: UC-048 | B18: Communication Gesture Recognition | C18: VISUAL-PRIMARY: Gesture recognition is visual. AUDIO-ENHANCED: Verbal acknowledgments ('roger', 'moving') complete the communication assessment.
A19: UC-049 | B19: Tactical Bound Timing and Coordination Assessment | C19: VISUAL-PRIMARY: Movement tracking is visual. AUDIO-ENHANCED: Detecting covering fire (esp. blank rounds) via audio is far more reliable.
A20: UC-050 | B20: After-Action Review Automated Highlight Generation | C20: AUDIO VALUABLE. Visual provides events; verbal commands and radio traffic are essential context for meaningful AAR.

Sheet Projects
B2: Project Name | C2: Policies
B3: Project A | C3: Policy - UC-001
C4: Policy - UC-002
C5: Policy - UC-003

Sheet Policy - TEMPLATE
A1: ▼ TYPE THE UC ID IN THE YELLOW CELL BELOW - EVERYTHING ELSE AUTO-FILLS ▼
B2: UC ID ↓
A4: IDENTIFICATION | B4: Use Case Name | C4: {=IFERROR(INDEX('Use Case Library'!B:T,MATCH(C2,'Use Case Library'!B:B,0),4),"")}
B5: Group | C5: {=IFERROR(INDEX('Use Case Library'!B:T,MATCH(C2,'Use Case Library'!B:B,0),2),"")}
B6: Category | C6: {=IFERROR(INDEX('Use Case Library'!B:T,MATCH(C2,'Use Case Library'!B:B,0),3),"")}
B7: Priority | C7: {=IFERROR(INDEX('Use Case Library'!B:T,MATCH(C2,'Use Case Library'!B:B,0),12),"")}
B8: Status | C8: {=IFERROR(INDEX('Use Case Library'!B:T,MATCH(C2,'Use Case Library'!B:B,0),13),"")}
B9: Detection Modality | C9: {=IFERROR(INDEX('Use Case Library'!B:T,MATCH(C2,'Use Case Library'!B:B,0),16),"")}
B10: Last Updated
A11: CONTEXT (auto-pulled - edit in Use Case Library, not here)
B12: Description | C12: {=IFERROR(INDEX('Use Case Library'!B:T,MATCH(C2,'Use Case Library'!B:B,0),5),"")}
B13: User Intent | C13: {=IFERROR(INDEX('Use Case Library'!B:T,MATCH(C2,'Use Case Library'!B:B,0),6),"")}
B14: Trigger / Detection Method | C14: {=IFERROR(INDEX('Use Case Library'!B:T,MATCH(C2,'Use Case Library'!B:B,0),7),"")}
B15: Key Behaviours to Track | C15: {=IFERROR(INDEX('Use Case Library'!B:T,MATCH(C2,'Use Case Library'!B:B,0),8),"")}
B16: Desired Outcome | C16: {=IFERROR(INDEX('Use Case Library'!B:T,MATCH(C2,'Use Case Library'!B:B,0),9),"")}
B17: Current Handling | C17: {=IFERROR(INDEX('Use Case Library'!B:T,MATCH(C2,'Use Case Library'!B:B,0),10),"")}
B18: Edge Cases (from library) | C18: {=IFERROR(INDEX('Use Case Library'!B:T,MATCH(C2,'Use Case Library'!B:B,0),11),"")}
B19: Dependencies | C19: {=IFERROR(INDEX('Use Case Library'!B:T,MATCH(C2,'Use Case Library'!B:B,0),15),"")}
B20: Current Policy Summary | C20: {=IFERROR(INDEX('Use Case Library'!B:T,MATCH(C2,'Use Case Library'!B:B,0),14),"")}
B21: Modality Rationale | C21: {=IFERROR(INDEX('Use Case Library'!B:T,MATCH(C2,'Use Case Library'!B:B,0),17),"")}
A22: DECISION LOGIC (fill manually - core deliverable)
B23: Step 1: Detection | C23: What signals indicate this use case is active? Classifiers, keywords, flags, thresholds.
B24: Step 2: Classification | C24: How do you determine severity or sub-type? What categories exist?
B25: Step 3: Response Selection | C25: What response strategy maps to each classification?
B26: Step 4: Execution | C26: What exactly does the system do? Be specific - templates, actions, tone.
B27: Step 5: Validation | C27: How verify the response was appropriate? Pre/post-delivery checks?
B28: Step 6: Follow-up | C28: What happens after initial response? Loops, escalation, closure.
B29: Algorithm (pseudocode / decision tree) | C29: Write complete if/then/else logic. IF [condition] THEN → [action] ELSE IF [condition] THEN → [action] ELSE → [default] END
A30: METRICS | B30: Success Metrics / KPIs | C30: How measure this is handled well?
B31: Failure Indicators | C31: What signals the policy is failing?
B32: Evaluation Method | C32: A/B test, manual review, automated checks?
A33: DETAILED EDGE CASES | B33: Edge Case 1
B34: → Handling
B35: Edge Case 2
B36: → Handling
B37: Edge Case 3
B38: → Handling
B39: Edge Case 4
B40: → Handling
A41: TEST CASES (input → expected → rationale)
B42: Test 1: Clear match - Input
B43: → Expected response
B44: → Why correct
B45: Test 2: Ambiguous - Input
B46: → Expected response
B47: → Why correct
B48: Test 3: False positive - Input
B49: → Expected response
B50: → Why correct
A51: REVIEW & SIGN-OFF | B51: Reviewed by
B52: Review date
B53: Approved by
B54: Approval date
B55: Version | C55: 1.0
A56: OPEN ITEMS | B56: Open Questions
B57: Decisions Needed
B58: Data Gaps
B59: Next Steps

Sheet Policy - UC-001
A1: ▼ TYPE THE UC ID IN THE YELLOW CELL BELOW - EVERYTHING ELSE AUTO-FILLS ▼
B2: UC ID ↓ | C2: UC-003
A4: IDENTIFICATION | B4: Use Case Name | C4: {=IFERROR(INDEX('Use Case Library'!B:T,MATCH(C2,'Use Case Library'!B:B,0),4),"")} -> Weapon Left Unattended Detection
B5: Group | C5: {=IFERROR(INDEX('Use Case Library'!B:T,MATCH(C2,'Use Case Library'!B:B,0),2),"")} -> A
B6: Category | C6: {=IFERROR(INDEX('Use Case Library'!B:T,MATCH(C2,'Use Case Library'!B:B,0),3),"")} -> Core Safety | E6: Project1
B7: Priority | C7: {=IFERROR(INDEX('Use Case Library'!B:T,MATCH(C2,'Use Case Library'!B:B,0),12),"")} -> P1 - High | F7: Policy 1
B8: Status | C8: {=IFERROR(INDEX('Use Case Library'!B:T,MATCH(C2,'Use Case Library'!B:B,0),13),"")} -> Not Started | F8: Policy 2 | G8: Configuration A (15 degrees, muzzle pointing direction)
B9: Detection Modality | C9: {=IFERROR(INDEX('Use Case Library'!B:T,MATCH(C2,'Use Case Library'!B:B,0),16),"")}
B10: Last Updated | C10: 46133 | E10: Project2
A11: REQUIREMENTS CONTEXT (auto-pulled - edit in Use Case Library, not here) | F11: Policy 2 | G11: Configuration B (10 degrees, muzzle pointing direction)
B12: Description | C12: {=IFERROR(INDEX('Use Case Library'!B:T,MATCH(C2,'Use Case Library'!B:B,0),5),"")} -> Detects a weapon stationary and not associated with any person in proximity - on ground, bench, or firing point with no one nearby - beyond a defined time threshold. | F12: Policy 3
B13: User Intent | C13: {=IFERROR(INDEX('Use Case Library'!B:T,MATCH(C2,'Use Case Library'!B:B,0),6),"")} -> No weapon should ever be left unsecured and unattended on a range.
B14: Trigger / Detection Method | C14: {=IFERROR(INDEX('Use Case Library'!B:T,MATCH(C2,'Use Case Library'!B:B,0),7),"")} -> Weapon-shaped object detection + human proximity check within defined radius + time-based trigger (e.g., 30s with no person within 2m). Focus on both day and night modes.
B15: Key Behaviours to Track | C15: {=IFERROR(INDEX('Use Case Library'!B:T,MATCH(C2,'Use Case Library'!B:B,0),8),"")} -> 1) Time weapon is unattended before detection 2) Distance to nearest person when flagged 3) Location context (firing point vs walkway vs rest area) 4) False positive rate (training props, weapon racks)
B16: Desired Outcome | C16: {=IFERROR(INDEX('Use Case Library'!B:T,MATCH(C2,'Use Case Library'!B:B,0),9),"")} -> Alert to nearest safety officer with weapon location, camera feed, and duration unattended. By default: If no external system integration is needed, it will then route the notification and alert to Accel.
B17: Current Handling | C17: {=IFERROR(INDEX('Use Case Library'!B:T,MATCH(C2,'Use Case Library'!B:B,0),10),"")} -> Discovered during physical checks or when someone reports a found weapon.
B18: Edge Cases (from library) | C18: {=IFERROR(INDEX('Use Case Library'!B:T,MATCH(C2,'Use Case Library'!B:B,0),11),"")} -> - Weapons deliberately placed in racks (authorised) - Training props / dummy weapons - Weapon placed down momentarily during drill change - Partial occlusion (under bench, behind bag)
B19: Dependencies | C19: {=IFERROR(INDEX('Use Case Library'!B:T,MATCH(C2,'Use Case Library'!B:B,0),15),"")} -> UC-008
B20: Current Policy Summary | C20: {=IFERROR(INDEX('Use Case Library'!B:T,MATCH(C2,'Use Case Library'!B:B,0),14),"")} -> Weapon Left Unattended IF weapon detected with no person within 2m radius for > 30s → ALERT to nearest safety officer. IF weapon is in designated rack/storage zone → suppress (authorised placement). IF weapon unattended > 120s anywhere → escalate to URGENT. Reset timer when any person enters 2m radius.
B21: Modality Rationale | C21: {=IFERROR(INDEX('Use Case Library'!B:T,MATCH(C2,'Use Case Library'!B:B,0),17),"")} -> Visual Only
A22: INFLUENCED TECHNOLOGIES REFERENCE
B23: AAAAAAA | C23: www.aaaa.com
A25: DECISION LOGIC (fill manually - core deliverable)
B26: Step 1: Detection | C26: The system needs to detect two things simultaneously: (a) the weapon's muzzle direction vector, and (b) the positions of all other persons in the frame. The muzzle vector is derived from weapon pose estimation, identifying the barrel axis from the receiver to muzzle tip. This requires the weapon to be at least partially visible. The system calculates the angular relationship between the muzzle vector and every detected person within a defined range (e.g., 30m forward arc). A "sweep" event is triggered when the muzzle-to-person angle falls below a threshold, I'd start at 15° cone, but this needs calibration with real range footage. Detection runs continuously at frame rate on all firing line cameras. | E26: CV Team to fill and maintain.
B27: Step 2: Classification | C27: Not all sweeps are equal. Classification axes: Duration: Transient (<2s) vs Sustained (≥2s). Transient sweeps happen during legitimate weapon transitions, going from slung to ready, changing firing position, or moving along the firing line. Sustained sweeps indicate either negligence or loss of awareness. Context: Firer stationary vs in motion. A sweep during movement (transitioning between positions) is less severe than a sweep while stationary. Proximity: How close is the swept person? A sweep across someone 2m away is far more dangerous than across someone 25m away at the end of the line. Weapon state: If weapon is in SLUNG state (from UC-008), muzzle may point near others but with no intent, lower severity. If weapon is in AIMED or HIGH-READY, any sweep is high severity. Classification matrix: CRITICAL: Sustained + stationary + aimed/high-ready + person within 3m HIGH: Sustained + any context + person within 5m MEDIUM: Transient + repeated (2nd+ occurrence in session) OR sustained + person beyond 10m LOW: Single transient during movement transition
B28: Step 3: Response Selection | C28: CRITICAL → Immediate audio/visual alert to Range Safety Officer (RSO) + auto-capture screenshot + recommend individual ceasefire for that position HIGH → Immediate alert to RSO + auto-capture. No ceasefire recommendation but RSO briefed to intervene directly. MEDIUM → Alert queued (non-interrupting notification to RSO). Logged for post-session review and UC-010 pattern tracking. LOW → Log only. No real-time alert. Feeds into UC-010 aggregate.
B29: Step 4: Execution | C29: On CRITICAL/HIGH trigger: (a) System freezes the relevant camera frame with muzzle vector overlay drawn on image (showing the firer, the vector, and the swept person highlighted) (b) Alert pushed to RSO tablet/screen: "MUZZLE VIOLATION — Lane [X], [severity], [firer description by position], [swept person description by position], [duration]s" (c) 5-second video clip buffered (2s before, 3s after event start) and attached to alert (d) If CRITICAL: audible alarm tone on RSO device + text overlay on range control display (e) Event logged with: timestamp, camera ID, firer position, swept person position, angle, duration, weapon state, classification On MEDIUM/LOW: (a) Event logged with same data fields (b) MEDIUM events appear in RSO's notification queue (reviewable between serials) (c) LOW events visible only in post-session reports
B30: Step 5: Validation | C30: Pre-delivery: Before alerting RSO, system performs a 0.5s confirmation check - is the detection sustained across multiple frames? Single-frame detections are suppressed (likely noise). This prevents alert fatigue from momentary classification errors. Post-delivery: RSO has a "Confirm / Dismiss" option on each alert. Confirmed alerts feed into UC-010. Dismissed alerts are logged as false positives and fed back for model retraining. Track the confirm/dismiss ratio - if dismiss rate > 30%, the threshold needs recalibration.
B31: Step 6: Follow-up | C31: (a) After any CRITICAL alert: system flags the individual for enhanced monitoring for remainder of session (tighter thresholds, lower duration requirement for alert) (b) After session: generate per-individual safety report showing all muzzle events (severity, frequency, trend) (c) If pattern detected across session (≥3 events, any severity): auto-generate UC-010 referral (d) RSO can mark an individual as "under remedial supervision" which persists across sessions
B32: Algorithm (pseudocode / decision tree) | C32: ON EACH FRAME: FOR each detected weapon W with identifiable muzzle vector: FOR each detected person P where P ≠ holder of W: angle = calculate_angle(W.muzzle_vector, P.position) distance = calculate_distance(W.holder.position, P.position) IF angle < SWEEP_THRESHOLD (15°): START or CONTINUE sweep_event for (W, P) sweep_event.duration += frame_interval sweep_event.weapon_state = get_weapon_state(W) // from UC-008 sweep_event.holder_moving = is_in_motion(W.holder) sweep_event.min_distance = min(sweep_event.min_distance, distance) // Classify IF sweep_event.duration ≥ 2s: IF weapon_state IN [AIMED, HIGH_READY] AND distance < 3m AND NOT holder_moving: severity = CRITICAL ELSE IF distance < 10m: severity = HIGH ELSE: severity = MEDIUM ELSE: IF count_session_events(W.holder) ≥ 2: severity = MEDIUM ELSE: severity = LOW // Confirm (multi-frame validation) IF sweep_event.consecutive_frames ≥ CONFIRM_FRAMES (3): IF severity IN [CRITICAL, HIGH]: SEND immediate_alert(RSO, sweep_event) CAPTURE video_clip(camera, timestamp, ±buffer) IF severity == CRITICAL: TRIGGER audible_alarm() RECOMMEND individual_ceasefire(W.holder.position) ELSE IF severity == MEDIUM: QUEUE notification(RSO, sweep_event) LOG event(sweep_event) UPDATE uc010_aggregate(W.holder, sweep_event) ELSE: IF active sweep_event exists for (W, P): CLOSE sweep_event // Final log with total duration
A33: METRICS
B34: Success Metrics / KPIs | C34: (a) Detection rate: % of actual muzzle violations detected (target: >90%, validated against manual review of sample footage) (b) Alert latency: time from violation start to RSO notification (target: <3s for CRITICAL/HIGH) (c) RSO confirmation rate: % of alerts confirmed as genuine by RSO (target: >70% - below this means too many false positives) (d) Intervention rate: % of CRITICAL/HIGH alerts where RSO took action within 30s (e) Zero miss rate on CRITICAL: no sustained aimed sweep at close range should ever go undetected (target: 100%) | E34: Fill by PM / QA
B35: Failure Indicators | C35: (a) RSO dismissing >30% of alerts → threshold too sensitive, alert fatigue risk (b) RSO ignoring alerts entirely (no confirm/dismiss action) → alert delivery or UI problem, or RSO has lost trust in system (c) Post-incident review reveals muzzle violation occurred but was not detected → detection model failure, need camera coverage or model review (d) Significant variation in detection rate between camera positions → coverage gap or angle-dependent model weakness
B36: Evaluation Method | C36: (a) Weekly sample review: randomly select 20 minutes of footage per range, have safety officer manually annotate violations, compare against system detections (precision and recall) (b) Monthly RSO feedback session: structured debrief on alert quality, false positive patterns, missed events (c) Quarterly threshold review: analyse all confirmed and dismissed alerts, adjust angle threshold and duration thresholds based on data (d) Annual model retraining with accumulated labelled data (confirmed alerts + manual annotations)
A37: DETAILED EDGE CASES | E37: Written by PM, handling to be decided by the CV Team.
B38: Edge Case 1 | C38: Momentary sweep during stance transition (e.g., standing to kneeling)
B39: → Handling | C39: Weapon state transition detected via UC-008 (state changing from one posture to another within a 3s window). During detected transitions, suppress CRITICAL/HIGH alerts and downgrade to LOG-only. If transition takes longer than 3s, resume normal thresholds, prolonged transition suggests fumbling, which is itself a safety concern.
B40: Edge Case 2 | C40: Weapon with mounted optic, bipod, or suppressor that obscures or extends the muzzle line
B41: → Handling | C41: The muzzle vector estimation model must be trained on weapons with common attachments. If the system cannot confidently determine muzzle direction (confidence < 0.6), log as INDETERMINATE and flag for camera repositioning recommendation. Do not suppress alerts - if anything, lower confidence should make the system more cautious, not less. Accept higher false positive rate rather than miss a genuine violation.
B42: Edge Case 3 | C42: Multiple people in frame with overlapping positions, system cannot determine which person was swept
B43: → Handling | C43: Alert on ALL persons within the sweep cone. The RSO can determine which specific individual was at risk. Better to over-report the swept persons than under-report. Log all persons in the cone with their respective angles and distances.
B44: Edge Case 4 | C44: Prone firing position where muzzle naturally points along the ground toward adjacent lanes
B45: → Handling | C45: When firer is classified as PRONE (via pose estimation) and weapon state is AIMED, apply a modified detection zone, the lateral sweep threshold is tightened (10° instead of 15°) but the forward arc is expanded to account for natural barrel movement during prone adjustments. If adjacent lane personnel are also PRONE and behind cover/in their own firing position, reduce severity by one level (they are in an expected exposure posture).
A46: Policy Governance
B47: Fail-safe stance Declaration | C47: FAIL-SAFE STANCE: When uncertain → [ALERT / LOG / SUSPEND / SAFE-STATE] When sensors fail → [raise threshold / downgrade / alert operator] When model confidence drops below floor → [specific action] When conflicting signals → [rule for arbitration] Example (UC-001): "If muzzle vector confidence < 0.5 AND weapon is visibly raised → treat as HIGH-READY and apply standard thresholds. Never silently discard a low-confidence detection of a raised weapon." | E47: Every policy should explicitly declare what the system does when it loses confidence, loses sensors, or can't decide. Right now there's no concept of a "fail-safe stance" — the system's default behaviour under uncertainty is undefined. For life-safety systems, the default must be conservative and stated explicitly.
B48: Authority & Liability Delineation | C48: AUTHORITY BOUNDARY: The system MAY: → Detect and classify events → Alert the Range Safety Officer → Recommend ceasefire → Pre-stage electronic range disable (for RSO to confirm) → Log all events with timestamps The system MAY NOT: → Command a ceasefire autonomously → Disable firing points without RSO confirmation → Identify individuals for disciplinary action → Be used as sole evidence in formal proceedings HUMAN IN THE LOOP requirement: All actions with physical consequences (ceasefire, range lockdown) require explicit RSO confirmation. System recommendations are advisory only. Decision authority: RSO has override power on ALL alerts. | E48: No policy defines where the system's authority ends and the human's begins. For a system that recommends ceasefires, this is legally critical. Who is liable if a recommendation is ignored and someone is hurt? Who is liable if the recommendation fires incorrectly and disrupts a critical exercise? These lines must be drawn explicitly in every P0/P1 policy.
A49: TEST CASES (input → expected → rationale) | E49: Written by PM / QA, handling to be decided by the CV Team.
B50: Test 1: Clear match - Input | C50: Firer at Lane 4, standing, weapon in HIGH-READY state. Turns to speak to person 3m to their right. Weapon muzzle traverses across that person's torso and remains pointed at them for 4 seconds.
B51: → Expected response | C51: CRITICAL alert. Immediate RSO notification with screenshot showing muzzle vector overlay crossing the adjacent person. Video clip captured. Audible alarm. Individual ceasefire recommendation for Lane 4.
B52: → Why correct | C52: Sustained (4s > 2s threshold) + HIGH-READY weapon state + person within 5m + firer stationary = maximum severity. All CRITICAL criteria met. This is textbook negligent muzzle discipline.
B53: Test 2: Ambiguous - Input | C53: Firer at Lane 7 is transitioning from standing to kneeling position. During the 1.5s transition, the weapon muzzle briefly passes through the 15° cone of the person at Lane 8 (distance: 2m). The weapon state is changing from HIGH-READY to AIMED (kneeling).
B54: → Expected response | C54: LOG only (no real-time alert). Event recorded with: transient (1.5s), during stance transition, first occurrence in session. Classified as LOW. If this is the firer's 3rd such event in the session, reclassify as MEDIUM and queue RSO notification.
B55: → Why correct | C55: Duration < 2s AND firer in detected motion/transition AND first occurrence = LOW severity. The stance transition context suppresses the alert. However, the event is still logged and counts toward UC-010 pattern accumulation - repeated transitions that sweep others suggest poor weapon handling technique even if each individual event is brief.
B56: Test 3: False positive - Input | C56: Camera captures a firer at Lane 2 whose weapon has a long suppressor attached. The suppressor creates a shadow that the system initially interprets as the muzzle pointing 20° off from actual direction. System calculates this phantom vector as sweeping a person at Lane 3.
B57: → Expected response | C57: System should NOT alert if the muzzle vector confidence is below threshold (0.6). Instead, log as INDETERMINATE with a flag for review. If the system's confidence is above 0.6 (it genuinely believes this is the muzzle direction), it SHOULD alert - the alert will be dismissed by the RSO as a false positive, and this dismissed event feeds back into model retraining for suppressor-equipped weapons.
B58: → Why correct | C58: We deliberately accept false positives over false negatives for safety-critical detection. The RSO dismiss action is the feedback loop. If suppressor-related false positives become frequent, this drives a specific model retraining cycle for that attachment type. The system should never silently suppress what it believes is a genuine detection.
A59: REVIEW & SIGN-OFF
B60: Reviewed by | C60: NA
B61: Review date | C61: NA
B62: Approved by | C62: Dan Lim
B63: Approval date | C63: 46133
B64: Version | C64: 1.0
A65: OPEN ITEMS
B66: Open Questions | C66: (a) What is the right angular threshold? 15° is a starting point but needs validation with real range footage. Should it vary by weapon type (pistol arc vs rifle arc)? (b) Should the system distinguish between "muzzle swept an instructor/RSO" (who accepts the risk by being on the line) vs "muzzle swept a fellow trainee" (who has no such expectation)? (c) How do we handle designated safety arcs that are range-specific? The system needs to ingest range-specific safe arc definitions per exercise, not just person-relative angles.
B67: Decisions Needed | C67: (a) Confirm severity classification matrix with Range Safety establishment - do they agree with the CRITICAL/HIGH/MEDIUM/LOW breakdown? (b) Define RSO alert delivery mechanism - tablet push notification? Overhead display? Audible alarm type? This affects latency targets. (c) Policy on alert fatigue: what is the maximum acceptable alert rate per hour before RSOs start ignoring them? This constrains threshold tuning.
B68: Data Gaps | C68: (a) No labelled training dataset of muzzle violations exists - need to either stage scenarios for initial training or manually annotate existing range footage (b) Weapon attachment configurations (suppressor, optic, bipod, grenade launcher) and their impact on muzzle vector estimation are untested (c) RSO dismiss rate baseline unknown - need to establish what "good" looks like before we can detect degradation
B69: Next Steps | C69: (a) Source or generate 50+ hours of range footage with diverse weapon types and positions for model training (b) Stage 20 controlled muzzle violation scenarios (various severities) for initial detection validation (c) Conduct RSO user testing - put alert UI in front of 3-5 RSOs and measure response time, comprehension, and trust (d) Define range-specific safe arc format and ingestion method (per-exercise configuration)

Sheet Policy - UC-002 (V1.0)
A1: ▼ TYPE THE UC ID IN THE YELLOW CELL BELOW - EVERYTHING ELSE AUTO-FILLS ▼
B2: UC ID ↓ | C2: UC-002
A4: IDENTIFICATION | B4: Use Case Name | C4: {=IFERROR(INDEX('Use Case Library'!B:T,MATCH(C2,'Use Case Library'!B:B,0),4),"")} -> Unauthorized Person in Danger Zone
B5: Group | C5: {=IFERROR(INDEX('Use Case Library'!B:T,MATCH(C2,'Use Case Library'!B:B,0),2),"")} -> A
B6: Category | C6: {=IFERROR(INDEX('Use Case Library'!B:T,MATCH(C2,'Use Case Library'!B:B,0),3),"")} -> Core Safety
B7: Priority | C7: {=IFERROR(INDEX('Use Case Library'!B:T,MATCH(C2,'Use Case Library'!B:B,0),12),"")} -> P0 - Critical
B8: Status | C8: {=IFERROR(INDEX('Use Case Library'!B:T,MATCH(C2,'Use Case Library'!B:B,0),13),"")} -> Not Started
B9: Detection Modality | C9: {=IFERROR(INDEX('Use Case Library'!B:T,MATCH(C2,'Use Case Library'!B:B,0),16),"")}
B10: Last Updated
A11: CONTEXT (auto-pulled - edit in Use Case Library, not here)
B12: Description | C12: {=IFERROR(INDEX('Use Case Library'!B:T,MATCH(C2,'Use Case Library'!B:B,0),5),"")} -> Detects a human figure entering a designated danger zone or downrange area while the (live/simulated) range is in operation. Could be a range worker, lost individual, or animal false positive.
B13: User Intent | C13: {=IFERROR(INDEX('Use Case Library'!B:T,MATCH(C2,'Use Case Library'!B:B,0),6),"")} -> Prevent any person from being in the impact area or danger zone during (live/simulated) fire.
B14: Trigger / Detection Method | C14: {=IFERROR(INDEX('Use Case Library'!B:T,MATCH(C2,'Use Case Library'!B:B,0),7),"")} -> Person detection (human body classifier) + geofenced zone overlay on camera feed + range status integration (hot/cold). Focus on both day and night modes.
B15: Key Behaviours to Track | C15: {=IFERROR(INDEX('Use Case Library'!B:T,MATCH(C2,'Use Case Library'!B:B,0),8),"")} -> 1) Detection confidence score 2) Time from zone entry (seen on camera) to alert (latency) 3) False positive rate (animals, shadows, vegetation) 4) Distance from nearest active firing point
B16: Desired Outcome | C16: {=IFERROR(INDEX('Use Case Library'!B:T,MATCH(C2,'Use Case Library'!B:B,0),9),"")} -> Immediate range-wide ceasefire recommendation with location overlay and camera feed to range control. By default: If no external system integration is needed, it will then route the notification and alert to Accel.
B17: Current Handling | C17: {=IFERROR(INDEX('Use Case Library'!B:T,MATCH(C2,'Use Case Library'!B:B,0),10),"")} -> Physical sentries and range guards with binoculars - limited visibility, fatigue, no night capability.
B18: Edge Cases (from library) | C18: {=IFERROR(INDEX('Use Case Library'!B:T,MATCH(C2,'Use Case Library'!B:B,0),11),"")} -> - Animal intrusion triggering false alert - Heat shimmer / mirage causing phantom detections - Authorised range party in zone during brief ceasefire windows - Person partially occluded by terrain
B19: Dependencies | C19: {=IFERROR(INDEX('Use Case Library'!B:T,MATCH(C2,'Use Case Library'!B:B,0),15),"")} -> UC-006, UC-027
B20: Current Policy Summary | C20: {=IFERROR(INDEX('Use Case Library'!B:T,MATCH(C2,'Use Case Library'!B:B,0),14),"")} -> Unauthorized Person in Danger Zone IF human detected in geofenced danger zone AND range status = HOT → immediate CEASEFIRE RECOMMENDATION to range control. IF confidence < 0.7 → flag for human verification before ceasefire call. IF entity classified as animal → LOG, no ceasefire. IF range status = COLD → LOG as administrative entry, no alert.
B21: Modality Rationale | C21: {=IFERROR(INDEX('Use Case Library'!B:T,MATCH(C2,'Use Case Library'!B:B,0),17),"")} -> Visual Only
A22: DECISION LOGIC (fill manually - core deliverable)
B23: Step 1: Detection | C23: The system needs to answer one question: is there a human being inside a defined danger zone? This breaks down into sub-problems. Zone definition: Danger zones are not simple rectangles. They are irregular polygons defined by weapon trajectory fans, ricochet zones, and terrain features. Each exercise type has a different danger zone template, and the range officer may modify it based on the specific exercise plan. The system must ingest zone definitions as georeferenced polygons, then project those polygons onto each camera's field of view using the camera's known position, angle, and lens calibration. This projection must be pre-computed before the exercise starts - you cannot do this in real time. Human detection at range: This is the hard part. At 50m, a person subtends hundreds of pixels on a typical HD camera - easy. At 300m, a person might be 15-20 pixels tall. At 500m+, a person is a handful of pixels indistinguishable from a fence post. The detection method must be distance-aware: (a) Near zone (0-100m): Standard person detection (full body classifier). High confidence achievable. Frame rate detection. (b) Mid zone (100-300m): Person detection still possible but confidence drops. Supplement with motion detection - a stationary person may not be classifiable, but a moving person produces a motion signature distinguishable from vegetation. Thermal/IR cameras significantly outperform visible spectrum at this range. (c) Far zone (300m+): Visual person detection unreliable. Primary detection shifts to motion anomaly (something moving that isn't vegetation or known range equipment) and thermal signature (human body heat stands out against terrain, especially at dawn/dusk/night). Accept that stationary persons in far zone may not be detected by camera alone - this is where range procedures (physical sweep before going hot) remain the primary control. Multi-camera fusion: A single camera detection at 200m+ should trigger a verification sequence - slew a PTZ camera to the location, or cross-reference with the nearest fixed camera that has a different angle. Single-camera single-frame detections at distance should never directly trigger a ceasefire - the false positive cost is too high.
B24: Step 2: Classification | C24: Every detection gets classified on two axes: Entity type: (a) HUMAN (high confidence ≥ 0.8) - body shape, gait, thermal profile consistent with human (b) HUMAN (low confidence 0.5-0.8) - something that could be human but uncertain (c) VEHICLE - larger signature, distinct shape and motion profile (d) ANIMAL - movement pattern (four-legged gait), size profile, thermal signature (usually lower and more distributed than human) (e) UNKNOWN - motion or thermal anomaly that doesn't classify into above (f) ENVIRONMENTAL - known false positive sources: heat shimmer, vegetation movement in wind, dust devil, shadow movement from clouds Authorisation status: (a) EXPECTED - position matches a known authorised presence (e.g., target operator in a designated target bunker during a known ceasefire window). The system must maintain a list of authorised positions and time windows. (b) UNEXPECTED - no matching authorisation. This is the default classification for any detection not matched to an authorised presence. (c) PREVIOUSLY CLEARED - the zone was swept and cleared, and the access points show no subsequent entry. This increases the suspicion level of any detection (something appeared in a zone that should be empty). Severity matrix: refer to right hand side table
B25: Step 3: Response Selection | C25: (a) CRITICAL → Immediate ceasefire recommendation. This is the only use case in the entire system that should have the authority to recommend a full range ceasefire, not just a lane ceasefire. The system does not command a ceasefire - it recommends to the range officer who makes the call. But the recommendation must be impossible to miss. (b) HIGH → Immediate alert to range officer with live camera feed slewed to detection location. PTZ camera auto-tracks the detection. If verification confirms human, escalate to CRITICAL. (c) MEDIUM → Alert queued for range officer. Log with camera capture. No ceasefire recommendation. (d) VERIFY → System auto-initiates verification sequence (PTZ slew, multi-camera cross-reference, thermal overlay). Alert to range officer: "Verifying detection at [grid reference]. Stand by." (e) LOG → Animal or environmental. Logged for pattern analysis (if the same area triggers repeatedly, the camera may need repositioning or the zone boundary may need adjustment). (f) SUPPRESS → Known environmental false positive. Not shown to range officer. Logged internally for system health monitoring.
B26: Step 4: Execution | C26: On CRITICAL: (1) Range control display flashes RED with detection location overlaid on range map (2) Audio alarm in range control tower - distinct from all other alarms (this is the "someone is downrange" alarm, it must be unmistakable) (3) All camera feeds showing the detection location are pushed to the primary display (4) If PTZ camera available, auto-slew to detection coordinates and begin tracking (5) System displays recommended action: "HUMAN DETECTED IN DANGER ZONE - CEASEFIRE RECOMMENDED - [grid ref] - [distance from nearest firing point]" (6) If range has electronic firing controls (lane enable/disable), system pre-stages a full range disable for the range officer to confirm with a single action (7) Continuous tracking of the detection - if the person is moving, display predicted path and whether they are moving toward or away from the impact area (8) Auto-record all camera feeds from detection point onward (incident preservation) On HIGH: (1) Alert to range officer with camera feed and location (2) PTZ auto-slew for verification (3) If verification confirms human within 30 seconds → escalate to CRITICAL (4) If verification cannot confirm (inconclusive) → maintain HIGH, alert stays active, range officer must make a judgment call (5) If verification confirms non-human → downgrade to LOG, clear alert On VERIFY: (1) PTZ slew and zoom to detection coordinates (2) Thermal camera overlay if available (3) Check detection against authorised presence list (is a target operator scheduled at that position?) (4) Present verification package to range officer within 15 seconds (5) Range officer confirms (→ escalate) or dismisses (→ log as false positive)
B27: Step 5: Validation | C27: Pre-alert validation (happens in <1 second): (a) Require detection in ≥3 consecutive frames before triggering alert (prevents single-frame noise) (b) Cross-reference against known static objects in the danger zone (range markers, target frames, structures). If the detection coordinates match a known static object within 2m, flag as potential false positive and require higher confidence (0.9) before alerting (c) Check for detection in multiple cameras if overlapping coverage exists. Multi-camera confirmation = automatic confidence boost (d) Environmental filter: if wind speed > 40km/h, increase motion detection threshold to compensate for vegetation movement. If temperature > 35°C, increase heat shimmer suppression filters Post-alert validation: (a) Range officer has CONFIRM / DISMISS / UNCERTAIN options (b) CONFIRM: incident logged, feeds into training data as true positive (c) DISMISS: logged as false positive with officer's noted reason. If the same detection source generates >5 dismissals in a session, flag the camera/zone for calibration review (d) UNCERTAIN: alert remains active until resolved. System continues tracking. (e) Track false positive rate per camera, per zone, per time-of-day, per weather condition - identify systematic false positive patterns
B28: Step 6: Follow-up | C28: After any CRITICAL event: (a) Range remains in ceasefire until the range officer positively confirms the danger zone is clear (either the person is accounted for and removed, or the detection is conclusively confirmed as false positive) (b) Incident report auto-generated with: timeline, all camera feeds, detection confidence log, range officer actions and timing (c) If person is found in the danger zone: formal incident investigation triggered. System data becomes evidence - all feeds preserved with chain-of-custody metadata (d) If false positive: root cause analysis. Was it animal, environmental, or model error? Feed back into detection improvement After any session: (a) Generate danger zone detection summary: total alerts by severity, false positive rate, detection locations heatmap (b) Flag any detection that occurred within 60 seconds of firing commencing or resuming - these represent the highest-risk near-misses even if resolved safely
B29: Algorithm (pseudocode / decision tree) | C29: CONTINUOUS MONITORING LOOP: // Pre-exercise: zone setup ON EXERCISE_START: LOAD danger_zone_polygons from exercise plan PROJECT polygons onto each camera FOV LOAD authorised_presence_list (position, time_windows) LOAD known_static_objects in zone VERIFY all cameras covering zone are operational IF any zone area has no camera coverage → ALERT range officer: blind spot at [location] // Real-time detection ON EACH FRAME for each camera covering danger zone: detections = run_detector(frame, zone_mask) FOR each detection D: // Static object filter IF D.position matches known_static_object within 2m: IF D.confidence < 0.9: CLASSIFY as ENVIRONMENTAL → SUPPRESS CONTINUE // Environmental filter IF matches_vegetation_motion_pattern(D) AND wind_speed > threshold: CLASSIFY as ENVIRONMENTAL → SUPPRESS CONTINUE // Entity classification entity_type = classify_entity(D) // HUMAN_HIGH, HUMAN_LOW, VEHICLE, ANIMAL, UNKNOWN IF entity_type == ANIMAL: LOG(D, "animal") CONTINUE // Frame persistence check IF D not tracked in previous 2 frames: INITIATE track, DO NOT alert yet CONTINUE IF D tracked ≥ 3 consecutive frames: // Authorisation check auth_status = check_authorisation(D.position, current_time, authorised_list) range_status = get_range_status() // HOT, CEASEFIRE, COLD severity = lookup_severity_matrix(entity_type, auth_status, range_status) IF severity == CRITICAL: TRIGGER ceasefire_recommendation() PUSH all_camera_feeds(D.position) SLEW PTZ_camera(D.position) PLAY distinct_alarm("danger_zone_intrusion") DISPLAY "HUMAN IN DANGER ZONE" on range_control PRE_STAGE electronic_range_disable() START continuous_tracking(D) START incident_recording() AWAIT range_officer_action() ELSE IF severity == HIGH: ALERT range_officer(D, camera_feed) SLEW PTZ_camera(D.position) START verification_timer(30s) ON verification_timer_expiry: IF D still tracked AND entity_type confirmed HUMAN: ESCALATE to CRITICAL ELSE IF D lost OR reclassified: DOWNGRADE and LOG ELSE IF severity == VERIFY: INITIATE verification_sequence(D) PRESENT to range_officer within 15s ELSE IF severity == MEDIUM: QUEUE alert for range_officer LOG(D) ELSE: LOG(D) // Post-CRITICAL resolution ON CRITICAL_RESOLUTION: IF person_found: TRIGGER formal_incident_investigation() PRESERVE all feeds with chain_of_custody() IF false_positive: LOG root_cause UPDATE detection_model_feedback RANGE remains CEASEFIRE until range_officer explicitly clears
A30: METRICS | B30: Success Metrics / KPIs | C30: (a) Detection rate for staged intrusions: Conduct quarterly tests where a person enters the danger zone during a controlled (non-live-fire) scenario. Target: 100% detection at ≤100m, >95% at 100-300m, >80% at 300m+ (visible spectrum), >90% at 300m+ (with thermal) (b) Alert latency: Time from person entering zone boundary to range officer receiving alert. Target: <5s for near zone (0-100m), <10s for mid zone (100-300m), <15s for far zone (300m+). These include the 3-frame persistence check. (c) False positive rate per session: Number of CRITICAL or HIGH alerts that are dismissed by range officer, divided by total alerts. Target: <15%. Below 5% is excellent. Above 25% means the system is creating dangerous alert fatigue. (d) False negative rate: This is the one that cannot be tolerated. Any missed detection of an actual person in the danger zone during a live-fire exercise is a system failure. Target: 0%. Measured via quarterly staged tests and post-exercise footage review. (e) Time to ceasefire: From CRITICAL alert to actual ceasefire execution by range officer. This measures the human response, not the system, but the system should track it. Target: <15s. If consistently >30s, the alert mechanism isn't effective enough. (f) Coverage completeness: Percentage of danger zone area covered by at least one camera. Target: 100% for near zone, >90% for mid zone. Blind spots must be documented and compensated by procedural controls.
B31: Failure Indicators | C31: (a) Any CRITICAL alert where the range officer takes >60s to respond → the alert mechanism is failing (not attention-grabbing enough, too many competing alerts, poor UI placement) (b) False positive rate rising over time → environmental conditions changing (new vegetation growth, new structures), camera calibration drifting, or model degrading (c) Repeated false positives from the same location → known static object not in the object database, or persistent environmental source (e.g., a flag or banner that moves in wind) (d) Post-exercise footage review finds a person was in the zone and system did not alert → immediate system failure investigation. Determine: was the person in a camera blind spot? Was the detection below confidence threshold? Was the environmental filter too aggressive? (e) Range officers begin pre-emptively silencing or ignoring alerts → the most dangerous failure mode. System credibility has been lost. Usually caused by sustained false positive rate >30%
B32: Evaluation Method | C32: (a) Quarterly staged intrusion test: Controlled scenario - a person enters the danger zone from different directions, distances, and in different conditions (daylight, dusk, thermal, rain, heat). Measure detection rate, latency, and classification accuracy. This is non-negotiable - you must test this proactively, not wait for a real incident. (b) Monthly false positive audit: Review all dismissed alerts from the past month. Categorise root causes (animal, environmental, model error, static object). Identify patterns. Feed false positives into model retraining. (c) Per-session automated report: System auto-generates a detection summary after every exercise showing: total detections by classification, alerts by severity, range officer response times, and any blind spot warnings. (d) Annual camera coverage audit: Walk every danger zone with GPS and verify camera coverage against the claimed coverage map. Identify new obstructions (tree growth, new structures) that have created blind spots since last audit. (e) Cross-reference with UC-035 (access logging): After every exercise, reconcile danger zone detections against access point entry/exit logs. If someone entered the range but is not accounted for by exit logs or personnel count (UC-006), that is an unresolved discrepancy requiring investigation regardless of whether the danger zone cameras detected them.
A33: DETAILED EDGE CASES | B33: Edge Case 1 | C33: Animal intrusion - deer, dog, or bird triggers detection
B34: → Handling | C34: The entity classifier must distinguish human from animal based on: body aspect ratio (four-legged vs bipedal), gait pattern (animal gait cycles are distinct from human walking/running), thermal profile (animals have lower, more distributed thermal signatures than clothed humans), and size at estimated distance. For birds, the vertical position (above ground plane) and flight motion pattern are sufficient filters. However, if the classifier confidence between HUMAN and ANIMAL is close (e.g., 55% animal, 45% human), treat as UNKNOWN and escalate to HIGH, not suppress as animal. At distance, a crawling person can look remarkably like a large dog in visible spectrum. The thermal profile is the tiebreaker - a crawling person's thermal signature is concentrated and elevated compared to a quadruped's. Accept false alerts from animals over missed detections of humans.
B35: Edge Case 2 | C35: Heat shimmer / mirage at distance on a hot day
B36: → Handling | C36: Heat shimmer causes image distortion that can create apparent motion and phantom shapes, particularly at 200m+ over tarmac, sand, or bare earth on hot days (>30°C, low wind). Mitigation: the system should detect shimmer conditions by analysing image stability metrics (high-frequency spatial distortion without corresponding object motion). When shimmer is detected in a zone, raise the detection confidence threshold from 0.8 to 0.9 for HUMAN_HIGH classification in that zone, and switch to thermal as the primary detection channel (thermal imaging is less affected by visible-spectrum shimmer). Log the shimmer detection as an environmental condition. If shimmer is persistent across the entire danger zone, alert the range officer that visual detection reliability is degraded and recommend enhanced procedural controls (additional physical sentries, reduced exercise scope).
B37: Edge Case 3 | C37: Authorised target operator in a bunker during a scheduled ceasefire window
B38: → Handling | C38: The authorised presence list must include: person role, position (bunker/location), and valid time window (ceasefire start → ceasefire end). The system should detect the operator entering the zone during ceasefire (LOG as EXPECTED), track them continuously, and automatically escalate to CRITICAL if the range status transitions to HOT while the operator is still in the zone. This is a critical interlock - the range should not be able to go hot while an authorised person is still detected in the danger zone. If the operator exits the zone, the system should confirm exit and update the authorised presence status. If the operator is not detected exiting before the ceasefire window closes, the system should ALERT: "Target operator may still be in zone - confirm clear before resuming fire." This is one of the most life-critical interlocks in the entire system.
B39: Edge Case 4 | C39: Person entering from an unmonitored boundary (e.g., adjacent land, jungle edge, rear of range)
B40: → Handling | C40: Danger zones often have natural boundaries (tree lines, fences, terrain features) that are assumed to be impassable. The system cannot rely on access point logging (UC-035) to know about intrusions from unmonitored boundaries. Camera coverage must include these boundaries where possible. Where camera coverage doesn't extend (e.g., deep jungle), the system must acknowledge the blind spot - document it in the coverage map, flag it to the range officer before every exercise, and recommend procedural mitigations (physical patrols of boundary before going hot, barrier improvement, acoustic sensors). The system should never represent 100% coverage confidence when physical blind spots exist. Honest coverage reporting is a safety obligation.
A41: TEST CASES (input → expected → rationale)
B42: Test 1: Clear match - Input | C42: Range status: HOT. Exercise in progress. Camera covering mid-zone (200m downrange) detects a person walking across the danger zone from left to right. Detection confidence 0.92 (HUMAN_HIGH). No matching entry in authorised presence list. Person detected in 15 consecutive frames, clearly moving with bipedal gait. Thermal confirms single human heat signature
B43: → Expected response | C43: CRITICAL within 5 seconds of first detection (3-frame persistence = ~0.1s at 30fps, plus processing and alert delivery). Range control display flashes RED. Distinct alarm sounds. All cameras showing detection location pushed to primary display. PTZ auto-tracks the person. System displays: "HUMAN DETECTED IN DANGER ZONE - CEASEFIRE RECOMMENDED - Grid [X] - 200m from firing line - moving [direction] at [speed]." Electronic range disable pre-staged. Continuous tracking with predicted path. All feeds recording.
B44: → Why correct | C44: High-confidence human detection, no authorisation, range is hot - every condition for CRITICAL is met. The system must assume this is a real person in mortal danger until proven otherwise. Speed of response is everything. The ceasefire recommendation is a recommendation, not an automatic action - the range officer makes the final call, but the system has done everything possible to make that call fast and informed.
B45: Test 2: Ambiguous - Input | C45: Range status: HOT. Camera covering far zone (400m) detects motion. Entity classification returns: 52% UNKNOWN, 31% ANIMAL, 17% HUMAN. The detection persists across 20 frames but the entity is small, partially occluded by low scrub, and moving in a pattern that doesn't clearly match human or animal gait. Thermal camera is available but at this range, the thermal resolution is low - it confirms a small warm body but cannot definitively classify.
B46: → Expected response | C46: Range status: HOT. Camera covering far zone (400m) detects motion. Entity classification returns: 52% UNKNOWN, 31% ANIMAL, 17% HUMAN. The detection persists across 20 frames but the entity is small, partially occluded by low scrub, and moving in a pattern that doesn't clearly match human or animal gait. Thermal camera is available but at this range, the thermal resolution is low - it confirms a small warm body but cannot definitively classify.
B47: → Why correct | C47: At 400m with ambiguous classification, neither ignoring it nor immediately calling ceasefire is correct. The system buys 30 seconds for verification while ensuring the range officer is aware and watching. The escalation to CRITICAL after 30s of unresolved ambiguity reflects the principle: if you can't confirm it's NOT a person, treat it as a person. The 30-second window is not a delay - it's a structured verification protocol. During those 30 seconds, the PTZ camera may resolve the ambiguity. If it doesn't, the system fails safe (ceasefire).
B48: Test 3: False positive - Input | C48: Range status: HOT. Temperature 38°C, wind 5km/h. Camera covering mid-zone detects what appears to be a person standing at 250m. Detection confidence: 0.78 (HUMAN_LOW). The detection appears in the same location for 200+ frames (not moving). Cross-reference against known static objects: a range marker post exists at those coordinates (1.5m tall, painted dark). Thermal shows no elevated heat signature at the location - ambient temperature matches surroundings.
B49: → Expected response | C49: System identifies position match with known static object (range marker post, within 2m). Thermal shows no human heat signature. Classification downgraded from HUMAN_LOW to ENVIRONMENTAL. Alert suppressed. Logged internally with note: "Detection at [grid ref] matches known static object (range marker). No thermal signature. Suppressed." If this is a new false positive source (first occurrence at this location), flag for addition to the known static objects database. If this is a recurring detection (>5 times), auto-add to static objects with range officer confirmation.
B50: → Why correct | C50: The multi-layer validation works here: the static object database catches the spatial match, and the thermal layer provides independent confirmation that there's no human present. Neither layer alone is sufficient - a person could be standing next to a range marker (spatial match but thermal positive), or a new object could have appeared that's not in the database (no spatial match). Both layers agreeing = high confidence false positive. The system does NOT alert the range officer, which is the correct behaviour - alerting on every range marker every session would destroy credibility.
A51: REVIEW & SIGN-OFF | B51: Reviewed by
B52: Review date
B53: Approved by | C53: Dan Lim
B54: Approval date | C54: 46133
B55: Version | C55: 1.0
A56: OPEN ITEMS | B56: Open Questions | C56: (1) How should the system handle the transition from CEASEFIRE to HOT when target operators are withdrawing from the danger zone? There's a window where operators are walking out but haven't cleared the zone boundary yet. Should the system enforce a "zone clear" confirmation before the range officer can declare HOT? This is an interlock design question. (2) What is the acceptable false positive rate before range officers lose trust? Military research on alarm systems suggests >20-25% false alarm rate leads to "cry wolf" syndrome within weeks. But for a life-safety system, even a 10% false positive rate means 1 in 10 alerts is wrong, which is 1 in 10 opportunities for the officer to develop dismissive habits. This tension is unresolvable by engineering alone - it requires training and culture.
B57: Decisions Needed
B58: Data Gaps
B59: Next Steps

Sheet Policy - UC-002 (V1.1)
A1: ▼ TYPE THE UC ID IN THE YELLOW CELL BELOW - EVERYTHING ELSE AUTO-FILLS ▼
B2: UC ID ↓ | C2: UC-002
A4: IDENTIFICATION | B4: Use Case Name | C4: {=IFERROR(INDEX('Use Case Library'!B:T,MATCH(C2,'Use Case Library'!B:B,0),4),"")} -> Unauthorized Person in Danger Zone
B5: Group | C5: {=IFERROR(INDEX('Use Case Library'!B:T,MATCH(C2,'Use Case Library'!B:B,0),2),"")} -> A
B6: Category | C6: {=IFERROR(INDEX('Use Case Library'!B:T,MATCH(C2,'Use Case Library'!B:B,0),3),"")} -> Core Safety
B7: Priority | C7: {=IFERROR(INDEX('Use Case Library'!B:T,MATCH(C2,'Use Case Library'!B:B,0),12),"")} -> P0 - Critical
B8: Status | C8: {=IFERROR(INDEX('Use Case Library'!B:T,MATCH(C2,'Use Case Library'!B:B,0),13),"")} -> Not Started
B9: Detection Modality | C9: {=IFERROR(INDEX('Use Case Library'!B:T,MATCH(C2,'Use Case Library'!B:B,0),16),"")}
B10: Last Updated
A11: CONTEXT (auto-pulled - edit in Use Case Library, not here)
B12: Description | C12: {=IFERROR(INDEX('Use Case Library'!B:T,MATCH(C2,'Use Case Library'!B:B,0),5),"")} -> Detects a human figure entering a designated danger zone or downrange area while the (live/simulated) range is in operation. Could be a range worker, lost individual, or animal false positive.
B13: User Intent | C13: {=IFERROR(INDEX('Use Case Library'!B:T,MATCH(C2,'Use Case Library'!B:B,0),6),"")} -> Prevent any person from being in the impact area or danger zone during (live/simulated) fire.
B14: Trigger / Detection Method | C14: {=IFERROR(INDEX('Use Case Library'!B:T,MATCH(C2,'Use Case Library'!B:B,0),7),"")} -> Person detection (human body classifier) + geofenced zone overlay on camera feed + range status integration (hot/cold). Focus on both day and night modes.
B15: Key Behaviours to Track | C15: {=IFERROR(INDEX('Use Case Library'!B:T,MATCH(C2,'Use Case Library'!B:B,0),8),"")} -> 1) Detection confidence score 2) Time from zone entry (seen on camera) to alert (latency) 3) False positive rate (animals, shadows, vegetation) 4) Distance from nearest active firing point
B16: Desired Outcome | C16: {=IFERROR(INDEX('Use Case Library'!B:T,MATCH(C2,'Use Case Library'!B:B,0),9),"")} -> Immediate range-wide ceasefire recommendation with location overlay and camera feed to range control. By default: If no external system integration is needed, it will then route the notification and alert to Accel.
B17: Current Handling | C17: {=IFERROR(INDEX('Use Case Library'!B:T,MATCH(C2,'Use Case Library'!B:B,0),10),"")} -> Physical sentries and range guards with binoculars - limited visibility, fatigue, no night capability.
B18: Edge Cases (from library) | C18: {=IFERROR(INDEX('Use Case Library'!B:T,MATCH(C2,'Use Case Library'!B:B,0),11),"")} -> - Animal intrusion triggering false alert - Heat shimmer / mirage causing phantom detections - Authorised range party in zone during brief ceasefire windows - Person partially occluded by terrain
B19: Dependencies | C19: {=IFERROR(INDEX('Use Case Library'!B:T,MATCH(C2,'Use Case Library'!B:B,0),15),"")} -> UC-006, UC-027
B20: Current Policy Summary | C20: {=IFERROR(INDEX('Use Case Library'!B:T,MATCH(C2,'Use Case Library'!B:B,0),14),"")} -> Unauthorized Person in Danger Zone IF human detected in geofenced danger zone AND range status = HOT → immediate CEASEFIRE RECOMMENDATION to range control. IF confidence < 0.7 → flag for human verification before ceasefire call. IF entity classified as animal → LOG, no ceasefire. IF range status = COLD → LOG as administrative entry, no alert.
B21: Modality Rationale | C21: {=IFERROR(INDEX('Use Case Library'!B:T,MATCH(C2,'Use Case Library'!B:B,0),17),"")} -> Visual Only
A22: DECISION LOGIC (fill manually - core deliverable)
B23: Step 1: Detection | C23: What signals indicate this use case is active? Classifiers, keywords, flags, thresholds.
B24: Step 2: Classification | C24: How do you determine severity or sub-type? What categories exist?
B25: Step 3: Response Selection | C25: What response strategy maps to each classification?
B26: Step 4: Execution | C26: What exactly does the system do? Be specific - templates, actions, tone.
B27: Step 5: Validation | C27: How verify the response was appropriate? Pre/post-delivery checks?
B28: Step 6: Follow-up | C28: What happens after initial response? Loops, escalation, closure.
B29: Algorithm (pseudocode / decision tree) | C29: Write complete if/then/else logic. IF [condition] THEN → [action] ELSE IF [condition] THEN → [action] ELSE → [default] END
A30: METRICS | B30: Success Metrics / KPIs | C30: How measure this is handled well?
B31: Failure Indicators | C31: What signals the policy is failing?
B32: Evaluation Method | C32: A/B test, manual review, automated checks?
A33: DETAILED EDGE CASES | B33: Edge Case 1
B34: → Handling
B35: Edge Case 2
B36: → Handling
B37: Edge Case 3
B38: → Handling
B39: Edge Case 4
B40: → Handling
A41: TEST CASES (input → expected → rationale)
B42: Test 1: Clear match - Input
B43: → Expected response
B44: → Why correct
B45: Test 2: Ambiguous - Input
B46: → Expected response
B47: → Why correct
B48: Test 3: False positive - Input
B49: → Expected response
B50: → Why correct
A51: REVIEW & SIGN-OFF | B51: Reviewed by
B52: Review date
B53: Approved by
B54: Approval date
B55: Version | C55: 1.1
A56: OPEN ITEMS | B56: Open Questions
B57: Decisions Needed
B58: Data Gaps
B59: Next Steps

Sheet Policy - UC-003
A1: ▼ TYPE THE UC ID IN THE YELLOW CELL BELOW - EVERYTHING ELSE AUTO-FILLS ▼
B2: UC ID ↓ | C2: UC-003
A4: IDENTIFICATION | B4: Use Case Name | C4: {=IFERROR(INDEX('Use Case Library'!B:T,MATCH(C2,'Use Case Library'!B:B,0),4),"")} -> Weapon Left Unattended Detection
B5: Group | C5: {=IFERROR(INDEX('Use Case Library'!B:T,MATCH(C2,'Use Case Library'!B:B,0),2),"")} -> A
B6: Category | C6: {=IFERROR(INDEX('Use Case Library'!B:T,MATCH(C2,'Use Case Library'!B:B,0),3),"")} -> Core Safety
B7: Priority | C7: {=IFERROR(INDEX('Use Case Library'!B:T,MATCH(C2,'Use Case Library'!B:B,0),12),"")} -> P1 - High
B8: Status | C8: {=IFERROR(INDEX('Use Case Library'!B:T,MATCH(C2,'Use Case Library'!B:B,0),13),"")} -> Not Started
B9: Detection Modality | C9: {=IFERROR(INDEX('Use Case Library'!B:T,MATCH(C2,'Use Case Library'!B:B,0),16),"")}
B10: Last Updated
A11: CONTEXT (auto-pulled - edit in Use Case Library, not here)
B12: Description | C12: {=IFERROR(INDEX('Use Case Library'!B:T,MATCH(C2,'Use Case Library'!B:B,0),5),"")} -> Detects a weapon stationary and not associated with any person in proximity - on ground, bench, or firing point with no one nearby - beyond a defined time threshold.
B13: User Intent | C13: {=IFERROR(INDEX('Use Case Library'!B:T,MATCH(C2,'Use Case Library'!B:B,0),6),"")} -> No weapon should ever be left unsecured and unattended on a range.
B14: Trigger / Detection Method | C14: {=IFERROR(INDEX('Use Case Library'!B:T,MATCH(C2,'Use Case Library'!B:B,0),7),"")} -> Weapon-shaped object detection + human proximity check within defined radius + time-based trigger (e.g., 30s with no person within 2m). Focus on both day and night modes.
B15: Key Behaviours to Track | C15: {=IFERROR(INDEX('Use Case Library'!B:T,MATCH(C2,'Use Case Library'!B:B,0),8),"")} -> 1) Time weapon is unattended before detection 2) Distance to nearest person when flagged 3) Location context (firing point vs walkway vs rest area) 4) False positive rate (training props, weapon racks)
B16: Desired Outcome | C16: {=IFERROR(INDEX('Use Case Library'!B:T,MATCH(C2,'Use Case Library'!B:B,0),9),"")} -> Alert to nearest safety officer with weapon location, camera feed, and duration unattended. By default: If no external system integration is needed, it will then route the notification and alert to Accel.
B17: Current Handling | C17: {=IFERROR(INDEX('Use Case Library'!B:T,MATCH(C2,'Use Case Library'!B:B,0),10),"")} -> Discovered during physical checks or when someone reports a found weapon.
B18: Edge Cases (from library) | C18: {=IFERROR(INDEX('Use Case Library'!B:T,MATCH(C2,'Use Case Library'!B:B,0),11),"")} -> - Weapons deliberately placed in racks (authorised) - Training props / dummy weapons - Weapon placed down momentarily during drill change - Partial occlusion (under bench, behind bag)
B19: Dependencies | C19: {=IFERROR(INDEX('Use Case Library'!B:T,MATCH(C2,'Use Case Library'!B:B,0),15),"")} -> UC-008
B20: Current Policy Summary | C20: {=IFERROR(INDEX('Use Case Library'!B:T,MATCH(C2,'Use Case Library'!B:B,0),14),"")} -> Weapon Left Unattended IF weapon detected with no person within 2m radius for > 30s → ALERT to nearest safety officer. IF weapon is in designated rack/storage zone → suppress (authorised placement). IF weapon unattended > 120s anywhere → escalate to URGENT. Reset timer when any person enters 2m radius.
B21: Modality Rationale | C21: {=IFERROR(INDEX('Use Case Library'!B:T,MATCH(C2,'Use Case Library'!B:B,0),17),"")} -> Visual Only
A22: DECISION LOGIC (fill manually - core deliverable)
B23: Step 1: Detection | C23: What signals indicate this use case is active? Classifiers, keywords, flags, thresholds.
B24: Step 2: Classification | C24: How do you determine severity or sub-type? What categories exist?
B25: Step 3: Response Selection | C25: What response strategy maps to each classification?
B26: Step 4: Execution | C26: What exactly does the system do? Be specific - templates, actions, tone.
B27: Step 5: Validation | C27: How verify the response was appropriate? Pre/post-delivery checks?
B28: Step 6: Follow-up | C28: What happens after initial response? Loops, escalation, closure.
B29: Algorithm (pseudocode / decision tree) | C29: Write complete if/then/else logic. IF [condition] THEN → [action] ELSE IF [condition] THEN → [action] ELSE → [default] END
A30: METRICS | B30: Success Metrics / KPIs | C30: How measure this is handled well?
B31: Failure Indicators | C31: What signals the policy is failing?
B32: Evaluation Method | C32: A/B test, manual review, automated checks?
A33: DETAILED EDGE CASES | B33: Edge Case 1
B34: → Handling
B35: Edge Case 2
B36: → Handling
B37: Edge Case 3
B38: → Handling
B39: Edge Case 4
B40: → Handling
A41: TEST CASES (input → expected → rationale)
B42: Test 1: Clear match - Input
B43: → Expected response
B44: → Why correct
B45: Test 2: Ambiguous - Input
B46: → Expected response
B47: → Why correct
B48: Test 3: False positive - Input
B49: → Expected response
B50: → Why correct
A51: REVIEW & SIGN-OFF | B51: Reviewed by
B52: Review date
B53: Approved by
B54: Approval date
B55: Version | C55: 1.0
A56: OPEN ITEMS | B56: Open Questions
B57: Decisions Needed
B58: Data Gaps
B59: Next Steps

Sheet Policy - UC-004
A1: ▼ TYPE THE UC ID IN THE YELLOW CELL BELOW - EVERYTHING ELSE AUTO-FILLS ▼
B2: UC ID ↓ | C2: UC-004
A4: IDENTIFICATION | B4: Use Case Name | C4: {=IFERROR(INDEX('Use Case Library'!B:T,MATCH(C2,'Use Case Library'!B:B,0),4),"")} -> Negligent / Accidental Discharge Detection
B5: Group | C5: {=IFERROR(INDEX('Use Case Library'!B:T,MATCH(C2,'Use Case Library'!B:B,0),2),"")} -> A
B6: Category | C6: {=IFERROR(INDEX('Use Case Library'!B:T,MATCH(C2,'Use Case Library'!B:B,0),3),"")} -> Core Safety
B7: Priority | C7: {=IFERROR(INDEX('Use Case Library'!B:T,MATCH(C2,'Use Case Library'!B:B,0),12),"")} -> P0 - Critical
B8: Status | C8: {=IFERROR(INDEX('Use Case Library'!B:T,MATCH(C2,'Use Case Library'!B:B,0),13),"")} -> Not Started
B9: Detection Modality | C9: {=IFERROR(INDEX('Use Case Library'!B:T,MATCH(C2,'Use Case Library'!B:B,0),16),"")}
B10: Last Updated
A11: CONTEXT (auto-pulled - edit in Use Case Library, not here)
B12: Description | C12: {=IFERROR(INDEX('Use Case Library'!B:T,MATCH(C2,'Use Case Library'!B:B,0),5),"")} -> Detects weapon discharge outside designated firing window or when range status is ceasefire/safe. Must distinguish actual discharge from camera artifacts.
B13: User Intent | C13: {=IFERROR(INDEX('Use Case Library'!B:T,MATCH(C2,'Use Case Library'!B:B,0),6),"")} -> Any unplanned discharge is a serious safety incident requiring immediate investigation.
B14: Trigger / Detection Method | C14: {=IFERROR(INDEX('Use Case Library'!B:T,MATCH(C2,'Use Case Library'!B:B,0),7),"")} -> Muzzle flash detection (1-2 frames) + recoil signature + ACOUSTIC GUNSHOT DETECTION for confirmation. Visual alone insufficient in daylight. Focus on both day and night modes. Necessary to consider audio cue from the live environment - adopt this as one of the primary verification layers.
B15: Key Behaviours to Track | C15: {=IFERROR(INDEX('Use Case Library'!B:T,MATCH(C2,'Use Case Library'!B:B,0),8),"")} -> 1) Detection confidence (visual-only vs audio-confirmed) 2) Exact timestamp and location 3) Range status at time of discharge 4) Direction of discharge relative to safe arc 5) Attribution: which position fired
B16: Desired Outcome | C16: {=IFERROR(INDEX('Use Case Library'!B:T,MATCH(C2,'Use Case Library'!B:B,0),9),"")} -> Immediate alert with multi-modal confirmation. Auto-log incident. Trigger ceasefire if range was supposed to be safe. The placement location of audio receiver in this case is important. Ensure the audio cue received is clear - this case may need to define the sound decibel to gauge the distance apart. By default: If no external system integration is needed, it will then route the notification and alert to Accel.
B17: Current Handling | C17: {=IFERROR(INDEX('Use Case Library'!B:T,MATCH(C2,'Use Case Library'!B:B,0),10),"")} -> Reported verbally by safety officers - delayed, sometimes missed in noisy environments.
B18: Edge Cases (from library) | C18: {=IFERROR(INDEX('Use Case Library'!B:T,MATCH(C2,'Use Case Library'!B:B,0),11),"")} -> - Daylight muzzle flash nearly invisible on camera - Blank rounds: flash but no recoil - Reflected light / camera artifact mimics flash - Suppressed weapons: minimal flash and report - Multiple simultaneous discharges
B19: Dependencies | C19: {=IFERROR(INDEX('Use Case Library'!B:T,MATCH(C2,'Use Case Library'!B:B,0),15),"")} -> UC-008, UC-026
B20: Current Policy Summary | C20: {=IFERROR(INDEX('Use Case Library'!B:T,MATCH(C2,'Use Case Library'!B:B,0),14),"")} -> Negligent / Accidental Discharge IF acoustic gunshot detected AND range status ≠ HOT → CRITICAL ALERT + auto-log incident. IF acoustic detected AND range status = HOT but outside firing window → ALERT. IF visual muzzle flash only (no acoustic confirm) → flag as UNCONFIRMED, request human verification. Always capture ±10s multi-camera footage around event timestamp.
B21: Modality Rationale | C21: {=IFERROR(INDEX('Use Case Library'!B:T,MATCH(C2,'Use Case Library'!B:B,0),17),"")} -> Visual + Audio
A22: DECISION LOGIC (fill manually - core deliverable)
B23: Step 1: Detection | C23: What signals indicate this use case is active? Classifiers, keywords, flags, thresholds.
B24: Step 2: Classification | C24: How do you determine severity or sub-type? What categories exist?
B25: Step 3: Response Selection | C25: What response strategy maps to each classification?
B26: Step 4: Execution | C26: What exactly does the system do? Be specific - templates, actions, tone.
B27: Step 5: Validation | C27: How verify the response was appropriate? Pre/post-delivery checks?
B28: Step 6: Follow-up | C28: What happens after initial response? Loops, escalation, closure.
B29: Algorithm (pseudocode / decision tree) | C29: Write complete if/then/else logic. IF [condition] THEN → [action] ELSE IF [condition] THEN → [action] ELSE → [default] END
A30: METRICS | B30: Success Metrics / KPIs | C30: How measure this is handled well?
B31: Failure Indicators | C31: What signals the policy is failing?
B32: Evaluation Method | C32: A/B test, manual review, automated checks?
A33: DETAILED EDGE CASES | B33: Edge Case 1
B34: → Handling
B35: Edge Case 2
B36: → Handling
B37: Edge Case 3
B38: → Handling
B39: Edge Case 4
B40: → Handling
A41: TEST CASES (input → expected → rationale)
B42: Test 1: Clear match - Input
B43: → Expected response
B44: → Why correct
B45: Test 2: Ambiguous - Input
B46: → Expected response
B47: → Why correct
B48: Test 3: False positive - Input
B49: → Expected response
B50: → Why correct
A51: REVIEW & SIGN-OFF | B51: Reviewed by
B52: Review date
B53: Approved by
B54: Approval date
B55: Version | C55: 1.0
A56: OPEN ITEMS | B56: Open Questions
B57: Decisions Needed
B58: Data Gaps
B59: Next Steps

Sheet Policy - UC-005
A1: ▼ TYPE THE UC ID IN THE YELLOW CELL BELOW - EVERYTHING ELSE AUTO-FILLS ▼
B2: UC ID ↓ | C2: UC-005
A4: IDENTIFICATION | B4: Use Case Name | C4: {=IFERROR(INDEX('Use Case Library'!B:T,MATCH(C2,'Use Case Library'!B:B,0),4),"")} -> Post-Firing Weapon Clearing Verification
B5: Group | C5: {=IFERROR(INDEX('Use Case Library'!B:T,MATCH(C2,'Use Case Library'!B:B,0),2),"")} -> A
B6: Category | C6: {=IFERROR(INDEX('Use Case Library'!B:T,MATCH(C2,'Use Case Library'!B:B,0),3),"")} -> Core Safety
B7: Priority | C7: {=IFERROR(INDEX('Use Case Library'!B:T,MATCH(C2,'Use Case Library'!B:B,0),12),"")} -> P0 - Critical
B8: Status | C8: {=IFERROR(INDEX('Use Case Library'!B:T,MATCH(C2,'Use Case Library'!B:B,0),13),"")} -> Not Started
B9: Detection Modality | C9: {=IFERROR(INDEX('Use Case Library'!B:T,MATCH(C2,'Use Case Library'!B:B,0),16),"")}
B10: Last Updated
A11: CONTEXT (auto-pulled - edit in Use Case Library, not here)
B12: Description | C12: {=IFERROR(INDEX('Use Case Library'!B:T,MATCH(C2,'Use Case Library'!B:B,0),5),"")} -> After ceasefire, visually monitors each firer performing clearing drill - magazine removal, bolt lock, chamber inspection - flags skipped or incorrect steps.
B13: User Intent | C13: {=IFERROR(INDEX('Use Case Library'!B:T,MATCH(C2,'Use Case Library'!B:B,0),6),"")} -> Verify every weapon is made safe before anyone moves from firing position.
B14: Trigger / Detection Method | C14: {=IFERROR(INDEX('Use Case Library'!B:T,MATCH(C2,'Use Case Library'!B:B,0),7),"")} -> Action sequence recognition: detect magazine removal → bolt manipulation → chamber check → show-clear gesture. Take note for night mode, where it can be dark, IR camera need to be considered.
B15: Key Behaviours to Track | C15: {=IFERROR(INDEX('Use Case Library'!B:T,MATCH(C2,'Use Case Library'!B:B,0),8),"")} -> 1) Clearing steps completed per individual 2) Steps skipped or out of order 3) Time from ceasefire to clearing complete 4) Individuals who walk away without clearing
B16: Desired Outcome | C16: {=IFERROR(INDEX('Use Case Library'!B:T,MATCH(C2,'Use Case Library'!B:B,0),9),"")} -> Checklist overlay per firing position. Flag incomplete clearings before range declared safe. By default: If no external system integration is needed, it will then route the notification and alert to Accel.
B17: Current Handling | C17: {=IFERROR(INDEX('Use Case Library'!B:T,MATCH(C2,'Use Case Library'!B:B,0),10),"")} -> Safety officer walks the line - slow, can miss detail with many firers.
B18: Edge Cases (from library) | C18: {=IFERROR(INDEX('Use Case Library'!B:T,MATCH(C2,'Use Case Library'!B:B,0),11),"")} -> - Belt-fed weapons have different clearing sequence - Pistols cleared differently than long arms - Body occludes weapon manipulation from certain angles - Speed of manipulation hard to resolve at standard frame rates
B19: Dependencies | C19: {=IFERROR(INDEX('Use Case Library'!B:T,MATCH(C2,'Use Case Library'!B:B,0),15),"")} -> UC-008, UC-006
B20: Current Policy Summary | C20: {=IFERROR(INDEX('Use Case Library'!B:T,MATCH(C2,'Use Case Library'!B:B,0),14),"")} -> Post-Firing Weapon Clearing Verification On CEASEFIRE event, initiate per-position monitoring. FOR EACH firer: track clearing sequence [magazine remove → bolt lock → chamber check → show-clear]. IF any step skipped → FLAG position as INCOMPLETE. IF firer leaves position before all steps confirmed → URGENT ALERT. Range not declared SAFE until all positions show COMPLETE.
B21: Modality Rationale | C21: {=IFERROR(INDEX('Use Case Library'!B:T,MATCH(C2,'Use Case Library'!B:B,0),17),"")} -> Visual Only
A22: DECISION LOGIC (fill manually - core deliverable)
B23: Step 1: Detection | C23: What signals indicate this use case is active? Classifiers, keywords, flags, thresholds.
B24: Step 2: Classification | C24: How do you determine severity or sub-type? What categories exist?
B25: Step 3: Response Selection | C25: What response strategy maps to each classification?
B26: Step 4: Execution | C26: What exactly does the system do? Be specific - templates, actions, tone.
B27: Step 5: Validation | C27: How verify the response was appropriate? Pre/post-delivery checks?
B28: Step 6: Follow-up | C28: What happens after initial response? Loops, escalation, closure.
B29: Algorithm (pseudocode / decision tree) | C29: Write complete if/then/else logic. IF [condition] THEN → [action] ELSE IF [condition] THEN → [action] ELSE → [default] END
A30: METRICS | B30: Success Metrics / KPIs | C30: How measure this is handled well?
B31: Failure Indicators | C31: What signals the policy is failing?
B32: Evaluation Method | C32: A/B test, manual review, automated checks?
A33: DETAILED EDGE CASES | B33: Edge Case 1
B34: → Handling
B35: Edge Case 2
B36: → Handling
B37: Edge Case 3
B38: → Handling
B39: Edge Case 4
B40: → Handling
A41: TEST CASES (input → expected → rationale)
B42: Test 1: Clear match - Input
B43: → Expected response
B44: → Why correct
B45: Test 2: Ambiguous - Input
B46: → Expected response
B47: → Why correct
B48: Test 3: False positive - Input
B49: → Expected response
B50: → Why correct
A51: REVIEW & SIGN-OFF | B51: Reviewed by
B52: Review date
B53: Approved by
B54: Approval date
B55: Version | C55: 1.0
A56: OPEN ITEMS | B56: Open Questions
B57: Decisions Needed
B58: Data Gaps
B59: Next Steps

Sheet Policy - UC-006
A1: ▼ TYPE THE UC ID IN THE YELLOW CELL BELOW - EVERYTHING ELSE AUTO-FILLS ▼
B2: UC ID ↓ | C2: UC-006
A4: IDENTIFICATION | B4: Use Case Name | C4: {=IFERROR(INDEX('Use Case Library'!B:T,MATCH(C2,'Use Case Library'!B:B,0),4),"")} -> Personnel Count and Position Reconciliation
B5: Group | C5: {=IFERROR(INDEX('Use Case Library'!B:T,MATCH(C2,'Use Case Library'!B:B,0),2),"")} -> A
B6: Category | C6: {=IFERROR(INDEX('Use Case Library'!B:T,MATCH(C2,'Use Case Library'!B:B,0),3),"")} -> Core Safety
B7: Priority | C7: {=IFERROR(INDEX('Use Case Library'!B:T,MATCH(C2,'Use Case Library'!B:B,0),12),"")} -> P0 - Critical
B8: Status | C8: {=IFERROR(INDEX('Use Case Library'!B:T,MATCH(C2,'Use Case Library'!B:B,0),13),"")} -> Not Started
B9: Detection Modality | C9: {=IFERROR(INDEX('Use Case Library'!B:T,MATCH(C2,'Use Case Library'!B:B,0),16),"")}
B10: Last Updated
A11: CONTEXT (auto-pulled - edit in Use Case Library, not here)
B12: Description | C12: {=IFERROR(INDEX('Use Case Library'!B:T,MATCH(C2,'Use Case Library'!B:B,0),5),"")} -> Continuously counts and maps all personnel against expected manifest. Detects: missing person, extra person, person in wrong position.
B13: User Intent | C13: {=IFERROR(INDEX('Use Case Library'!B:T,MATCH(C2,'Use Case Library'!B:B,0),6),"")} -> Know where every person on the range is at all times.
B14: Trigger / Detection Method | C14: {=IFERROR(INDEX('Use Case Library'!B:T,MATCH(C2,'Use Case Library'!B:B,0),7),"")} -> Multi-camera person detection + position mapping + manifest comparison.
B15: Key Behaviours to Track | C15: {=IFERROR(INDEX('Use Case Library'!B:T,MATCH(C2,'Use Case Library'!B:B,0),8),"")} -> 1) Count accuracy vs manifest 2) Position accuracy (correct lane/zone) 3) Time to detect discrepancy 4) Resilience to occlusion and grouping
B16: Desired Outcome | C16: {=IFERROR(INDEX('Use Case Library'!B:T,MATCH(C2,'Use Case Library'!B:B,0),9),"")} -> Real-time personnel map in range control. Instant alert on count mismatch or position deviation. By default: If no external system integration is needed, it will then route the notification and alert to Accel.
B17: Current Handling | C17: {=IFERROR(INDEX('Use Case Library'!B:T,MATCH(C2,'Use Case Library'!B:B,0),10),"")} -> Manual headcount at start and end of serials - no continuous tracking.
B18: Edge Cases (from library) | C18: {=IFERROR(INDEX('Use Case Library'!B:T,MATCH(C2,'Use Case Library'!B:B,0),11),"")} -> - Identical uniforms and gear - Clustering makes count difficult - Camera blind spots - People entering/exiting buildings or vehicles
B19: Dependencies | C19: {=IFERROR(INDEX('Use Case Library'!B:T,MATCH(C2,'Use Case Library'!B:B,0),15),"")} -> UC-045, UC-035
B20: Current Policy Summary | C20: {=IFERROR(INDEX('Use Case Library'!B:T,MATCH(C2,'Use Case Library'!B:B,0),14),"")} -> Personnel Count and Position Reconciliation On exercise start, lock manifest count. Continuous count at 5s intervals. IF count < manifest → MISSING PERSON alert (P0). IF count > manifest → EXTRA PERSON alert. IF individual deviates > 10m from assigned position → POSITION DEVIATION warning. Reconcile against UC-035 entry/exit log for discrepancy resolution.
B21: Modality Rationale | C21: {=IFERROR(INDEX('Use Case Library'!B:T,MATCH(C2,'Use Case Library'!B:B,0),17),"")} -> Visual Only
A22: DECISION LOGIC (fill manually - core deliverable)
B23: Step 1: Detection | C23: What signals indicate this use case is active? Classifiers, keywords, flags, thresholds.
B24: Step 2: Classification | C24: How do you determine severity or sub-type? What categories exist?
B25: Step 3: Response Selection | C25: What response strategy maps to each classification?
B26: Step 4: Execution | C26: What exactly does the system do? Be specific - templates, actions, tone.
B27: Step 5: Validation | C27: How verify the response was appropriate? Pre/post-delivery checks?
B28: Step 6: Follow-up | C28: What happens after initial response? Loops, escalation, closure.
B29: Algorithm (pseudocode / decision tree) | C29: Write complete if/then/else logic. IF [condition] THEN → [action] ELSE IF [condition] THEN → [action] ELSE → [default] END
A30: METRICS | B30: Success Metrics / KPIs | C30: How measure this is handled well?
B31: Failure Indicators | C31: What signals the policy is failing?
B32: Evaluation Method | C32: A/B test, manual review, automated checks?
A33: DETAILED EDGE CASES | B33: Edge Case 1
B34: → Handling
B35: Edge Case 2
B36: → Handling
B37: Edge Case 3
B38: → Handling
B39: Edge Case 4
B40: → Handling
A41: TEST CASES (input → expected → rationale)
B42: Test 1: Clear match - Input
B43: → Expected response
B44: → Why correct
B45: Test 2: Ambiguous - Input
B46: → Expected response
B47: → Why correct
B48: Test 3: False positive - Input
B49: → Expected response
B50: → Why correct
A51: REVIEW & SIGN-OFF | B51: Reviewed by
B52: Review date
B53: Approved by
B54: Approval date
B55: Version | C55: 1.0
A56: OPEN ITEMS | B56: Open Questions
B57: Decisions Needed
B58: Data Gaps
B59: Next Steps

Sheet Policy - UC-007
A1: ▼ TYPE THE UC ID IN THE YELLOW CELL BELOW - EVERYTHING ELSE AUTO-FILLS ▼
B2: UC ID ↓ | C2: UC-007
A4: IDENTIFICATION | B4: Use Case Name | C4: {=IFERROR(INDEX('Use Case Library'!B:T,MATCH(C2,'Use Case Library'!B:B,0),4),"")} -> Firing Line Breach Detection
B5: Group | C5: {=IFERROR(INDEX('Use Case Library'!B:T,MATCH(C2,'Use Case Library'!B:B,0),2),"")} -> A
B6: Category | C6: {=IFERROR(INDEX('Use Case Library'!B:T,MATCH(C2,'Use Case Library'!B:B,0),3),"")} -> Core Safety
B7: Priority | C7: {=IFERROR(INDEX('Use Case Library'!B:T,MATCH(C2,'Use Case Library'!B:B,0),12),"")} -> P0 - Critical
B8: Status | C8: {=IFERROR(INDEX('Use Case Library'!B:T,MATCH(C2,'Use Case Library'!B:B,0),13),"")} -> Not Started
B9: Detection Modality | C9: {=IFERROR(INDEX('Use Case Library'!B:T,MATCH(C2,'Use Case Library'!B:B,0),16),"")}
B10: Last Updated
A11: CONTEXT (auto-pulled - edit in Use Case Library, not here)
B12: Description | C12: {=IFERROR(INDEX('Use Case Library'!B:T,MATCH(C2,'Use Case Library'!B:B,0),5),"")} -> Detects when any person moves forward of the firing line during live-fire serial. Even partial step counts.
B13: User Intent | C13: {=IFERROR(INDEX('Use Case Library'!B:T,MATCH(C2,'Use Case Library'!B:B,0),6),"")} -> No person forward of the firing line while weapons are firing.
B14: Trigger / Detection Method | C14: {=IFERROR(INDEX('Use Case Library'!B:T,MATCH(C2,'Use Case Library'!B:B,0),7),"")} -> Person detection + firing line boundary definition in camera frame. Track foot position relative to line.
B15: Key Behaviours to Track | C15: {=IFERROR(INDEX('Use Case Library'!B:T,MATCH(C2,'Use Case Library'!B:B,0),8),"")} -> 1) Detection latency from breach to alert 2) Severity: partial step vs full breach 3) Distance forward of line 4) False positive rate from parallax
B16: Desired Outcome | C16: {=IFERROR(INDEX('Use Case Library'!B:T,MATCH(C2,'Use Case Library'!B:B,0),9),"")} -> Immediate alert. Automatic ceasefire recommendation if breach exceeds threshold. By default: If no external system integration is needed, it will then route the notification and alert to Accel.
B17: Current Handling | C17: {=IFERROR(INDEX('Use Case Library'!B:T,MATCH(C2,'Use Case Library'!B:B,0),10),"")} -> Range safety officer watches - can miss peripheral breaches.
B18: Edge Cases (from library) | C18: {=IFERROR(INDEX('Use Case Library'!B:T,MATCH(C2,'Use Case Library'!B:B,0),11),"")} -> - Firing line not physically marked (field firing) - Camera angle makes position ambiguous - Person drops object forward and reaches - Line changes between serials
B19: Dependencies | C19: {=IFERROR(INDEX('Use Case Library'!B:T,MATCH(C2,'Use Case Library'!B:B,0),15),"")} -> UC-006
B20: Current Policy Summary | C20: {=IFERROR(INDEX('Use Case Library'!B:T,MATCH(C2,'Use Case Library'!B:B,0),14),"")} -> Firing Line Breach Detection IF any person's foot position crosses firing line boundary AND range status = HOT → IMMEDIATE ALERT + ceasefire recommendation. IF breach < 0.5m and < 1s (momentary lean) → LOG as minor, no ceasefire. IF breach > 1m or sustained > 2s → CRITICAL, auto-recommend ceasefire. Update line boundary definition at each serial change.
B21: Modality Rationale | C21: {=IFERROR(INDEX('Use Case Library'!B:T,MATCH(C2,'Use Case Library'!B:B,0),17),"")} -> Visual Only
A22: DECISION LOGIC (fill manually - core deliverable)
B23: Step 1: Detection | C23: What signals indicate this use case is active? Classifiers, keywords, flags, thresholds.
B24: Step 2: Classification | C24: How do you determine severity or sub-type? What categories exist?
B25: Step 3: Response Selection | C25: What response strategy maps to each classification?
B26: Step 4: Execution | C26: What exactly does the system do? Be specific - templates, actions, tone.
B27: Step 5: Validation | C27: How verify the response was appropriate? Pre/post-delivery checks?
B28: Step 6: Follow-up | C28: What happens after initial response? Loops, escalation, closure.
B29: Algorithm (pseudocode / decision tree) | C29: Write complete if/then/else logic. IF [condition] THEN → [action] ELSE IF [condition] THEN → [action] ELSE → [default] END
A30: METRICS | B30: Success Metrics / KPIs | C30: How measure this is handled well?
B31: Failure Indicators | C31: What signals the policy is failing?
B32: Evaluation Method | C32: A/B test, manual review, automated checks?
A33: DETAILED EDGE CASES | B33: Edge Case 1
B34: → Handling
B35: Edge Case 2
B36: → Handling
B37: Edge Case 3
B38: → Handling
B39: Edge Case 4
B40: → Handling
A41: TEST CASES (input → expected → rationale)
B42: Test 1: Clear match - Input
B43: → Expected response
B44: → Why correct
B45: Test 2: Ambiguous - Input
B46: → Expected response
B47: → Why correct
B48: Test 3: False positive - Input
B49: → Expected response
B50: → Why correct
A51: REVIEW & SIGN-OFF | B51: Reviewed by
B52: Review date
B53: Approved by
B54: Approval date
B55: Version | C55: 1.0
A56: OPEN ITEMS | B56: Open Questions
B57: Decisions Needed
B58: Data Gaps
B59: Next Steps

Sheet Policy - UC-008
A1: ▼ TYPE THE UC ID IN THE YELLOW CELL BELOW - EVERYTHING ELSE AUTO-FILLS ▼
B2: UC ID ↓ | C2: UC-008
A4: IDENTIFICATION | B4: Use Case Name | C4: {=IFERROR(INDEX('Use Case Library'!B:T,MATCH(C2,'Use Case Library'!B:B,0),4),"")} -> Weapon Readiness State Classification
B5: Group | C5: {=IFERROR(INDEX('Use Case Library'!B:T,MATCH(C2,'Use Case Library'!B:B,0),2),"")} -> A
B6: Category | C6: {=IFERROR(INDEX('Use Case Library'!B:T,MATCH(C2,'Use Case Library'!B:B,0),3),"")} -> Core Safety
B7: Priority | C7: {=IFERROR(INDEX('Use Case Library'!B:T,MATCH(C2,'Use Case Library'!B:B,0),12),"")} -> P1 - High
B8: Status | C8: {=IFERROR(INDEX('Use Case Library'!B:T,MATCH(C2,'Use Case Library'!B:B,0),13),"")} -> Not Started
B9: Detection Modality | C9: {=IFERROR(INDEX('Use Case Library'!B:T,MATCH(C2,'Use Case Library'!B:B,0),16),"")}
B10: Last Updated
A11: CONTEXT (auto-pulled - edit in Use Case Library, not here)
B12: Description | C12: {=IFERROR(INDEX('Use Case Library'!B:T,MATCH(C2,'Use Case Library'!B:B,0),5),"")} -> Classifies observable weapon state: holstered/slung, low-ready, high-ready, aimed/shouldered, firing. Feeds into other use cases.
B13: User Intent | C13: {=IFERROR(INDEX('Use Case Library'!B:T,MATCH(C2,'Use Case Library'!B:B,0),6),"")} -> Continuous awareness of weapon states across the range.
B14: Trigger / Detection Method | C14: {=IFERROR(INDEX('Use Case Library'!B:T,MATCH(C2,'Use Case Library'!B:B,0),7),"")} -> Weapon detection + pose classification. Multi-class: slung, low-ready, high-ready, aimed, firing.
B15: Key Behaviours to Track | C15: {=IFERROR(INDEX('Use Case Library'!B:T,MATCH(C2,'Use Case Library'!B:B,0),8),"")} -> 1) Classification accuracy per state 2) State transition detection speed 3) Accuracy across weapon types 4) Robustness to occlusion from gear
B16: Desired Outcome | C16: {=IFERROR(INDEX('Use Case Library'!B:T,MATCH(C2,'Use Case Library'!B:B,0),9),"")} -> Real-time weapon state overlay. Anomaly detection: aimed during ceasefire, firing outside window.
B17: Current Handling | C17: {=IFERROR(INDEX('Use Case Library'!B:T,MATCH(C2,'Use Case Library'!B:B,0),10),"")} -> No automated tracking - entirely dependent on safety officer observation.
B18: Edge Cases (from library) | C18: {=IFERROR(INDEX('Use Case Library'!B:T,MATCH(C2,'Use Case Library'!B:B,0),11),"")} -> - Weapon partially hidden by body armour - Pistol states subtler than rifle - Slung weapon bouncing mimics state change - Night/IR conditions alter appearance
B19: Dependencies | C19: {=IFERROR(INDEX('Use Case Library'!B:T,MATCH(C2,'Use Case Library'!B:B,0),15),"")} -> UC-001, UC-004, UC-005
B20: Current Policy Summary | C20: {=IFERROR(INDEX('Use Case Library'!B:T,MATCH(C2,'Use Case Library'!B:B,0),14),"")} -> Weapon Readiness State Classification Continuous classification per tracked individual: SLUNG → LOW-READY → HIGH-READY → AIMED → FIRING. IF state = AIMED and range status ≠ HOT → ALERT. IF state = AIMED and firer not at designated firing position → ALERT. Feed state data to UC-001 (muzzle direction uses weapon state as input) and UC-004 (firing state outside window).
B21: Modality Rationale | C21: {=IFERROR(INDEX('Use Case Library'!B:T,MATCH(C2,'Use Case Library'!B:B,0),17),"")} -> Visual Only
A22: DECISION LOGIC (fill manually - core deliverable)
B23: Step 1: Detection | C23: What signals indicate this use case is active? Classifiers, keywords, flags, thresholds.
B24: Step 2: Classification | C24: How do you determine severity or sub-type? What categories exist?
B25: Step 3: Response Selection | C25: What response strategy maps to each classification?
B26: Step 4: Execution | C26: What exactly does the system do? Be specific - templates, actions, tone.
B27: Step 5: Validation | C27: How verify the response was appropriate? Pre/post-delivery checks?
B28: Step 6: Follow-up | C28: What happens after initial response? Loops, escalation, closure.
B29: Algorithm (pseudocode / decision tree) | C29: Write complete if/then/else logic. IF [condition] THEN → [action] ELSE IF [condition] THEN → [action] ELSE → [default] END
A30: METRICS | B30: Success Metrics / KPIs | C30: How measure this is handled well?
B31: Failure Indicators | C31: What signals the policy is failing?
B32: Evaluation Method | C32: A/B test, manual review, automated checks?
A33: DETAILED EDGE CASES | B33: Edge Case 1
B34: → Handling
B35: Edge Case 2
B36: → Handling
B37: Edge Case 3
B38: → Handling
B39: Edge Case 4
B40: → Handling
A41: TEST CASES (input → expected → rationale)
B42: Test 1: Clear match - Input
B43: → Expected response
B44: → Why correct
B45: Test 2: Ambiguous - Input
B46: → Expected response
B47: → Why correct
B48: Test 3: False positive - Input
B49: → Expected response
B50: → Why correct
A51: REVIEW & SIGN-OFF | B51: Reviewed by
B52: Review date
B53: Approved by
B54: Approval date
B55: Version | C55: 1.0
A56: OPEN ITEMS | B56: Open Questions
B57: Decisions Needed
B58: Data Gaps
B59: Next Steps

Sheet Policy - UC-009
A1: ▼ TYPE THE UC ID IN THE YELLOW CELL BELOW - EVERYTHING ELSE AUTO-FILLS ▼
B2: UC ID ↓ | C2: UC-009
A4: IDENTIFICATION | B4: Use Case Name | C4: {=IFERROR(INDEX('Use Case Library'!B:T,MATCH(C2,'Use Case Library'!B:B,0),4),"")} -> Medical Casualty Detection During Live Exercise
B5: Group | C5: {=IFERROR(INDEX('Use Case Library'!B:T,MATCH(C2,'Use Case Library'!B:B,0),2),"")} -> A
B6: Category | C6: {=IFERROR(INDEX('Use Case Library'!B:T,MATCH(C2,'Use Case Library'!B:B,0),3),"")} -> Core Safety
B7: Priority | C7: {=IFERROR(INDEX('Use Case Library'!B:T,MATCH(C2,'Use Case Library'!B:B,0),12),"")} -> P0 - Critical
B8: Status | C8: {=IFERROR(INDEX('Use Case Library'!B:T,MATCH(C2,'Use Case Library'!B:B,0),13),"")} -> Not Started
B9: Detection Modality | C9: {=IFERROR(INDEX('Use Case Library'!B:T,MATCH(C2,'Use Case Library'!B:B,0),16),"")}
B10: Last Updated
A11: CONTEXT (auto-pulled - edit in Use Case Library, not here)
B12: Description | C12: {=IFERROR(INDEX('Use Case Library'!B:T,MATCH(C2,'Use Case Library'!B:B,0),5),"")} -> Detects person falling, collapsing, or exhibiting distress postures while weapons are in play. Must distinguish genuine event from tactical movement.
B13: User Intent | C13: {=IFERROR(INDEX('Use Case Library'!B:T,MATCH(C2,'Use Case Library'!B:B,0),6),"")} -> Get medical help immediately, even when live fire creates access challenges. Especially critical when the casualty personnel is alone - often overlooked.
B14: Trigger / Detection Method | C14: {=IFERROR(INDEX('Use Case Library'!B:T,MATCH(C2,'Use Case Library'!B:B,0),7),"")} -> Fall detection (sudden vertical-to-horizontal) + stationary posture duration + context analysis.
B15: Key Behaviours to Track | C15: {=IFERROR(INDEX('Use Case Library'!B:T,MATCH(C2,'Use Case Library'!B:B,0),8),"")} -> 1) Time from collapse to detection 2) False positive rate (going prone intentionally vs fall) 3) Distinguishing tactical prone from distress 4) Context: expected vs unexpected posture for exercise phase
B16: Desired Outcome | C16: {=IFERROR(INDEX('Use Case Library'!B:T,MATCH(C2,'Use Case Library'!B:B,0),9),"")} -> Immediate alert to safety officer and medical team. Ceasefire recommendation for affected lane. By default: If no external system integration is needed, it will then route the notification and alert to Accel.
B17: Current Handling | C17: {=IFERROR(INDEX('Use Case Library'!B:T,MATCH(C2,'Use Case Library'!B:B,0),10),"")} -> Buddy or adjacent firer notices - delayed, sometimes missed during intense firing.
B18: Edge Cases (from library) | C18: {=IFERROR(INDEX('Use Case Library'!B:T,MATCH(C2,'Use Case Library'!B:B,0),11),"")} -> - Going prone is normal firing position - Simulated casualties in training - Person resting between serials - Gradual event (heat exhaustion) vs sudden collapse
B19: Dependencies | C19: {=IFERROR(INDEX('Use Case Library'!B:T,MATCH(C2,'Use Case Library'!B:B,0),15),"")} -> UC-006, UC-004
B20: Current Policy Summary | C20: {=IFERROR(INDEX('Use Case Library'!B:T,MATCH(C2,'Use Case Library'!B:B,0),14),"")} -> Medical Casualty Detection IF sudden vertical-to-horizontal transition detected AND person remains stationary > 10s AND context ≠ expected prone position → MEDICAL ALERT to safety officer + medical team. IF audio detects 'man down' call → bypass 10s wait, alert immediately. IF exercise phase expects prone firing → raise stationary threshold to 30s. Always recommend lane-specific ceasefire, not range-wide.
B21: Modality Rationale | C21: {=IFERROR(INDEX('Use Case Library'!B:T,MATCH(C2,'Use Case Library'!B:B,0),17),"")} -> Visual-Primary, Audio-Enhanced
A22: DECISION LOGIC (fill manually - core deliverable)
B23: Step 1: Detection | C23: What signals indicate this use case is active? Classifiers, keywords, flags, thresholds.
B24: Step 2: Classification | C24: How do you determine severity or sub-type? What categories exist?
B25: Step 3: Response Selection | C25: What response strategy maps to each classification?
B26: Step 4: Execution | C26: What exactly does the system do? Be specific - templates, actions, tone.
B27: Step 5: Validation | C27: How verify the response was appropriate? Pre/post-delivery checks?
B28: Step 6: Follow-up | C28: What happens after initial response? Loops, escalation, closure.
B29: Algorithm (pseudocode / decision tree) | C29: Write complete if/then/else logic. IF [condition] THEN → [action] ELSE IF [condition] THEN → [action] ELSE → [default] END
A30: METRICS | B30: Success Metrics / KPIs | C30: How measure this is handled well?
B31: Failure Indicators | C31: What signals the policy is failing?
B32: Evaluation Method | C32: A/B test, manual review, automated checks?
A33: DETAILED EDGE CASES | B33: Edge Case 1
B34: → Handling
B35: Edge Case 2
B36: → Handling
B37: Edge Case 3
B38: → Handling
B39: Edge Case 4
B40: → Handling
A41: TEST CASES (input → expected → rationale)
B42: Test 1: Clear match - Input
B43: → Expected response
B44: → Why correct
B45: Test 2: Ambiguous - Input
B46: → Expected response
B47: → Why correct
B48: Test 3: False positive - Input
B49: → Expected response
B50: → Why correct
A51: REVIEW & SIGN-OFF | B51: Reviewed by
B52: Review date
B53: Approved by
B54: Approval date
B55: Version | C55: 1.0
A56: OPEN ITEMS | B56: Open Questions
B57: Decisions Needed
B58: Data Gaps
B59: Next Steps

Sheet Policy - UC-010
A1: ▼ TYPE THE UC ID IN THE YELLOW CELL BELOW - EVERYTHING ELSE AUTO-FILLS ▼
B2: UC ID ↓ | C2: UC-010
A4: IDENTIFICATION | B4: Use Case Name | C4: {=IFERROR(INDEX('Use Case Library'!B:T,MATCH(C2,'Use Case Library'!B:B,0),4),"")} -> Unsafe Weapon Handling Behaviour Pattern Detection
B5: Group | C5: {=IFERROR(INDEX('Use Case Library'!B:T,MATCH(C2,'Use Case Library'!B:B,0),2),"")} -> A
B6: Category | C6: {=IFERROR(INDEX('Use Case Library'!B:T,MATCH(C2,'Use Case Library'!B:B,0),3),"")} -> Core Safety
B7: Priority | C7: {=IFERROR(INDEX('Use Case Library'!B:T,MATCH(C2,'Use Case Library'!B:B,0),12),"")} -> P2 - Medium
B8: Status | C8: {=IFERROR(INDEX('Use Case Library'!B:T,MATCH(C2,'Use Case Library'!B:B,0),13),"")} -> Not Started
B9: Detection Modality | C9: {=IFERROR(INDEX('Use Case Library'!B:T,MATCH(C2,'Use Case Library'!B:B,0),16),"")}
B10: Last Updated
A11: CONTEXT (auto-pulled - edit in Use Case Library, not here)
B12: Description | C12: {=IFERROR(INDEX('Use Case Library'!B:T,MATCH(C2,'Use Case Library'!B:B,0),5),"")} -> Identifies accumulated patterns of unsafe behaviour over time - repeated muzzle sweeps, finger on trigger while not firing, weapon manipulation during briefings. Trend indicates intervention needed.
B13: User Intent | C13: {=IFERROR(INDEX('Use Case Library'!B:T,MATCH(C2,'Use Case Library'!B:B,0),6),"")} -> Identify individuals developing unsafe habits before an incident occurs.
B14: Trigger / Detection Method | C14: {=IFERROR(INDEX('Use Case Library'!B:T,MATCH(C2,'Use Case Library'!B:B,0),7),"")} -> Aggregation of detections from UC-001, UC-008, UC-005 over time per individual. Statistical pattern analysis.
B15: Key Behaviours to Track | C15: {=IFERROR(INDEX('Use Case Library'!B:T,MATCH(C2,'Use Case Library'!B:B,0),8),"")} -> 1) Minor violations per individual per session 2) Trend over multiple sessions 3) Correlation between patterns and incident proximity 4) False pattern rate
B16: Desired Outcome | C16: {=IFERROR(INDEX('Use Case Library'!B:T,MATCH(C2,'Use Case Library'!B:B,0),9),"")} -> Flagged report to safety officer with evidence. Recommendation for remedial training. By default: If no external system integration is needed, it will then route the notification and alert to Accel.
B17: Current Handling | C17: {=IFERROR(INDEX('Use Case Library'!B:T,MATCH(C2,'Use Case Library'!B:B,0),10),"")} -> Anecdotal - no systematic tracking.
B18: Edge Cases (from library) | C18: {=IFERROR(INDEX('Use Case Library'!B:T,MATCH(C2,'Use Case Library'!B:B,0),11),"")} -> - New trainees expected to have more violations - Cultural differences between units - Pattern window: how far back to look? - Privacy/fairness concerns
B19: Dependencies | C19: {=IFERROR(INDEX('Use Case Library'!B:T,MATCH(C2,'Use Case Library'!B:B,0),15),"")} -> UC-001, UC-008, UC-005
B20: Current Policy Summary | C20: {=IFERROR(INDEX('Use Case Library'!B:T,MATCH(C2,'Use Case Library'!B:B,0),14),"")} -> Unsafe Weapon Handling Behaviour Pattern Aggregate violations from UC-001, UC-005, UC-008 per individual per session. IF minor violations ≥ 3 in single session → INTERVENTION ADVISORY to safety officer. IF violations trending upward across sessions (≥2 consecutive sessions above baseline) → REMEDIAL TRAINING recommendation. Weight recent violations higher. Exclude first-session trainees from trend analysis (learning curve allowance).
B21: Modality Rationale | C21: {=IFERROR(INDEX('Use Case Library'!B:T,MATCH(C2,'Use Case Library'!B:B,0),17),"")} -> Visual Only
A22: DECISION LOGIC (fill manually - core deliverable)
B23: Step 1: Detection | C23: What signals indicate this use case is active? Classifiers, keywords, flags, thresholds.
B24: Step 2: Classification | C24: How do you determine severity or sub-type? What categories exist?
B25: Step 3: Response Selection | C25: What response strategy maps to each classification?
B26: Step 4: Execution | C26: What exactly does the system do? Be specific - templates, actions, tone.
B27: Step 5: Validation | C27: How verify the response was appropriate? Pre/post-delivery checks?
B28: Step 6: Follow-up | C28: What happens after initial response? Loops, escalation, closure.
B29: Algorithm (pseudocode / decision tree) | C29: Write complete if/then/else logic. IF [condition] THEN → [action] ELSE IF [condition] THEN → [action] ELSE → [default] END
A30: METRICS | B30: Success Metrics / KPIs | C30: How measure this is handled well?
B31: Failure Indicators | C31: What signals the policy is failing?
B32: Evaluation Method | C32: A/B test, manual review, automated checks?
A33: DETAILED EDGE CASES | B33: Edge Case 1
B34: → Handling
B35: Edge Case 2
B36: → Handling
B37: Edge Case 3
B38: → Handling
B39: Edge Case 4
B40: → Handling
A41: TEST CASES (input → expected → rationale)
B42: Test 1: Clear match - Input
B43: → Expected response
B44: → Why correct
B45: Test 2: Ambiguous - Input
B46: → Expected response
B47: → Why correct
B48: Test 3: False positive - Input
B49: → Expected response
B50: → Why correct
A51: REVIEW & SIGN-OFF | B51: Reviewed by
B52: Review date
B53: Approved by
B54: Approval date
B55: Version | C55: 1.0
A56: OPEN ITEMS | B56: Open Questions
B57: Decisions Needed
B58: Data Gaps
B59: Next Steps

Sheet Policy - UC-051
A1: ▼ TYPE THE UC ID IN THE YELLOW CELL BELOW - EVERYTHING ELSE AUTO-FILLS ▼
B2: UC ID ↓ | C2: UC-051
A4: IDENTIFICATION | B4: Use Case Name | C4: {=IFERROR(INDEX('Use Case Library'!B:T,MATCH(C2,'Use Case Library'!B:B,0),4),"")} -> Weapon Visibility Rule (Consolidated)
B5: Group | C5: {=IFERROR(INDEX('Use Case Library'!B:T,MATCH(C2,'Use Case Library'!B:B,0),2),"")} -> J
B6: Category | C6: {=IFERROR(INDEX('Use Case Library'!B:T,MATCH(C2,'Use Case Library'!B:B,0),3),"")} -> SWT Weapons
B7: Priority | C7: {=IFERROR(INDEX('Use Case Library'!B:T,MATCH(C2,'Use Case Library'!B:B,0),12),"")} -> P0 - Critical
B8: Status | C8: {=IFERROR(INDEX('Use Case Library'!B:T,MATCH(C2,'Use Case Library'!B:B,0),13),"")} -> Draft
B9: Detection Modality | C9: {=IFERROR(INDEX('Use Case Library'!B:T,MATCH(C2,'Use Case Library'!B:B,0),16),"")} -> Configuration: "WEAPON_CONFIDENCE_THRESHOLD": 0.80 Minimum YOLO confidence for a weapon detection to count. Lower = more sensitive (more false positives). Higher = miss small/blurry weapons. "PERSON_CONFIDENCE_THRESHOLD": 0.80 Minimum YOLO confidence for a person detection to count. "T1_DURATION_THRESHOLD": 2.0 Seconds to wait before firing an URGENT alert. Used by: Missing, Taken, Boundary Violation (UC-052 uses 0s = immediate). "T2_DURATION_THRESHOLD": 5.0 Seconds to wait before firing a WARNING alert (longer grace period). Used by: Occluded scenarios (person standing near weapon). "NEAR_DISTANCE_PX": 200 THE KEY DISTANCE FOR UC-051. Pixel radius around the weapon's last-known position. Person within this distance = 'near' (occluded → T2). Person beyond this distance = 'far' (taken → T1).
B10: Last Updated
A11: CONTEXT (auto-pulled - edit in Use Case Library, not here)
B12: Description | C12: {=IFERROR(INDEX('Use Case Library'!B:T,MATCH(C2,'Use Case Library'!B:B,0),5),"")} -> Consolidated policy covering all scenarios where a weapon disappears from view within the detection zone. Handles three sub-scenarios based on person count at disappearance: (A) no person present, (B) one person — weapon taken out of frame or occluded, (C) multiple persons present. Merges original Policies 1, 2, and 3.
B13: User Intent | C13: {=IFERROR(INDEX('Use Case Library'!B:T,MATCH(C2,'Use Case Library'!B:B,0),6),"")} -> Ensure any weapon that is no longer visible triggers a timely alert once all associated persons have cleared the detection zone.
B14: Trigger / Detection Method | C14: {=IFERROR(INDEX('Use Case Library'!B:T,MATCH(C2,'Use Case Library'!B:B,0),7),"")} -> Weapon-shaped object classifier loses confirmed detection (absent ≥3 consecutive frames). Person-detection classifier tracks associated individuals in the zone. T1 and T2 timers govern alert timing based on person presence state.
B15: Key Behaviours to Track | C15: {=IFERROR(INDEX('Use Case Library'!B:T,MATCH(C2,'Use Case Library'!B:B,0),8),"")} -> 1) Weapon visibility state (visible / occluded / out-of-frame) 2) Associated person count in detection zone 3) T1 timer state (countdown after zone is clear) 4) T2 timer state (grace period while person remains) 5) Weapon reappearance events (timer reset trigger)
B16: Desired Outcome | C16: {=IFERROR(INDEX('Use Case Library'!B:T,MATCH(C2,'Use Case Library'!B:B,0),9),"")} -> Alert triggered after T1 expires once all associated persons have left and weapon remains unseen. If weapon reappears before T1 expires, all timers reset and no alert is issued.
B17: Current Handling | C17: {=IFERROR(INDEX('Use Case Library'!B:T,MATCH(C2,'Use Case Library'!B:B,0),10),"")} -> Manual observation. No automated tracking of weapon visibility state or person-presence changes.
B18: Edge Cases (from library) | C18: {=IFERROR(INDEX('Use Case Library'!B:T,MATCH(C2,'Use Case Library'!B:B,0),11),"")} -> - Weapon occluded by passing non-associated person - Person re-enters zone after T1 has started - Weapon reappears briefly then disappears again (reset-restart cycle) - Multiple persons leaving at different times
B19: Dependencies | C19: {=IFERROR(INDEX('Use Case Library'!B:T,MATCH(C2,'Use Case Library'!B:B,0),15),"")} -> Need to detect the object first and when a weapon detection disappears, the policy walks every LOCKED person and measures: distance = center_of_person_box → center_of_weapon's_last_known_position Then classifies: • distance ≤ NEAR_DISTANCE_PX (200 px) → 'near' → contributes to near_count • distance > NEAR_DISTANCE_PX (200 px) → 'far' → contributes to far_count • no locked persons in ROI at all → 'none'
B20: Config Variables | C20: {=IFERROR(INDEX('Use Case Library'!B:T,MATCH(C2,'Use Case Library'!B:B,0),16),"")} -> Configuration: "WEAPON_CONFIDENCE_THRESHOLD": 0.80 Minimum YOLO confidence for a weapon detection to count. Lower = more sensitive (more false positives). Higher = miss small/blurry weapons. "PERSON_CONFIDENCE_THRESHOLD": 0.80 Minimum YOLO confidence for a person detection to count. "T1_DURATION_THRESHOLD": 2.0 Seconds to wait before firing an URGENT alert. Used by: Missing, Taken, Boundary Violation (UC-052 uses 0s = immediate). "T2_DURATION_THRESHOLD": 5.0 Seconds to wait before firing a WARNING alert (longer grace period). Used by: Occluded scenarios (person standing near weapon). "NEAR_DISTANCE_PX": 200 THE KEY DISTANCE FOR UC-051. Pixel radius around the weapon's last-known position. Person within this distance = 'near' (occluded → T2). Person beyond this distance = 'far' (taken → T1).
B21: Current Policy Summary | C21: {=IFERROR(INDEX('Use Case Library'!B:T,MATCH(C2,'Use Case Library'!B:B,0),14),"")} -> IF weapon not visible AND 0 persons → start T1 (Weapon {Weapon_id} Missing) → alert. IF weapon not visible AND 1 person near → start T2 (Weapon {Weapon_id} Occluded by Person {Person_id) → alert. IF weapon not visible AND 1 person far → start T1(Weapon {Weapon_id} Taken by Person {Person_id)) → alert. IF weapon not visible AND 2+ persons → priority rules: ANY person far → T1 (Weapon {Weapon_id} Taken by Person {Person_id)) All 2+ persons near → T2 (Weapon {Weapon_id} Occluded by Person {Person_id)) 1 near, 0 far → T2 (Weapon {Weapon_id} Occluded by Person {Person_id)) All left ROI → T1(Weapon {Weapon_id} Taken by Person {Person_id)) IF weapon reappears before window expiry → reset all timers, no alert.
B22: Modality Rationale | C22: {=IFERROR(INDEX('Use Case Library'!B:T,MATCH(C2,'Use Case Library'!B:B,0),17),"")} -> Visual Only
B23: Step 1: Detection | C23: The system runs two YOLO classifiers in parallel each frame: (a) Weapon classifier (custom model) — outputs weapon bounding boxes with track IDs via ByteTrack (b) Person classifier (YOLO11) — outputs person bounding boxes with track IDs via ByteTrack Signals that activate this use case: - A baseline weapon track ID disappears (not detected in current frame) - The weapon is confirmed missing only after absence is sustained across frames (track ID drops out of YOLO output) Configurable thresholds (credentials.json): - WEAPON_CONFIDENCE_THRESHOLD = 0.80 (minimum confidence to count as detected) - PERSON_CONFIDENCE_THRESHOLD = 0.80 - T1_DURATION_THRESHOLD = seconds before T1 alert fires - T2_DURATION_THRESHOLD = seconds for T2 grace period (occluded scenarios) - NEAR_DISTANCE_PX = 200 px (radius defining 'person near weapon') - ASSOCIATION_DISTANCE = auto-scaled to screen width (typ. 200–600 px)
B24: Step 2: Classification | C24: At the moment a weapon disappears, classify into one of three sub-scenarios based on associated person count and proximity: SUB-SCENARIO A — 0 persons associated in ROI → proximity = 'none' or 'visible' → No one was near the weapon when it vanished SUB-SCENARIO B — 1 person associated B1: Person is FAR from last known weapon position (> ASSOCIATION_DISTANCE) → proximity = 'far' → likely weapon was carried out of frame B2: Person is NEAR last known weapon position (≤ NEAR_DISTANCE_PX) → proximity = 'near' → likely weapon is occluded by person SUB-SCENARIO C — 2+ persons associated Subdivides dynamically as persons leave: - 2+ persons still near → T2 - 1 person remains near → degrades to B2 logic (T2) - all persons gone → degrades to A logic (T1) Person count is tracked via weapon_person_lock (active) and missing_weapon_locks (after weapon disappears), keyed by weapon track ID.
B25: Step 3: Response Selection | C25: PolicyEvaluator.evaluate_visibility() returns (window_seconds, label, suppress) per sub-scenario: Sub-Scenario A (no person) → window = T1, label = 'UC-051(A: NoPerson→T1)' Sub-Scenario B1 (1 person far) → window = T1, label = 'UC-051(B1: Taken→T1)' Sub-Scenario B2 (1 person near) → window = T2, label = 'UC-051(B2: Occluded→T2)' Sub-Scenario C (2+ persons near) → suppress = True, no timer runs Sub-Scenario C → 1 remains → window = T2, label = 'UC-051(C→B: OneRemains→T2)' Sub-Scenario C → all left → window = T1, label = 'UC-051(C→A: AllLeft→T1)' If weapon reappears at any point before window expires → all timers reset, no alert fired. UC-052 (Boundary Violation) takes priority — if both fire, UC-052 wins and UC-051 is skipped for that weapon.
B26: Step 4: Execution | C26: On timer expiry (elapsed ≥ window_seconds): 1. Mark weapon state: alert_active = True, alert_start_frame = current frame 2. Set active_policy_label (e.g., 'UC-051(B2: Occluded→T2)') 3. Add HUD popup with mapped alarm category via PolicyEvaluator.alarm_category_for_label(): 'Weapon Missing' (Sub-Scenario A) 'Weapon Taken' (Sub-Scenario B1) 'Weapon Occluded' (Sub-Scenario B2 or C→B) 4. Play audio cue via PolicyEvaluator.beep_type_for_label(): beep_type = 0 → alert_T1.wav (T1 paths — urgent tone) beep_type = 1 → alert_T2.wav (T2 paths — warning tone) Audio is rate-limited (BEEP_DELAY_SECONDS = 2.0s) to prevent overlap. 5. Draw YELLOW dashed box at last known weapon position with label 'Missing ID{wid} ({elapsed:.1f}s)' 6. Emit frame_and_state signal with state['alert_active'] = True for UI rendering 7. If SAVE_VIDEO_OUTPUT = true, write annotated frame to output_videos/{source}_{timestamp}.mp4
B27: Step 5: Validation | C27: Pre-alert validation (every frame while timer runs): (a) Track ID confirmation — weapon must be missing across multiple frames (ByteTrack persistence prevents single-frame dropout false triggers) (b) Reappearance remapping — if a new track ID appears within REAPPEAR_DISTANCE_PX (500 px) of the missing weapon's last position OR overlaps its last bounding box, transfer state to the new ID (cancels the pending alert and clears missing_start_frame) (c) Window extension check — if proximity changes from 'far' (T1) to 'near' (T2) before T1 expires, reset alert_active flag so the longer T2 window applies (d) Multi-person suppression refresh — if 2+ persons re-enter near the weapon while in Sub-Scenario C, force missing_start_frame = current_frame each tick (timer never advances) Post-alert: (a) Alert remains active until either: - Weapon reappears (track ID detected again within REAPPEAR_DISTANCE_PX of last known position) - Detection is stopped (S key) → tracker._prev_start_state resets, baseline recaptured on next start (b) When weapon reappears: missing_start_frame, alert_active, alert_start_frame, and active_policy_label all cleared in tracker.weapon_states[wid]
B28: Step 6: Follow-up | C28: After alert is triggered: (a) Alert stays on HUD until weapon reappears OR operator stops detection (b) Console log records: ROI ID, weapon ID, policy label, elapsed time, T1/T2 thresholds, proximity state, locked person counts (c) Annotated video continuously written to output_videos/ if SAVE_VIDEO_OUTPUT = true (d) Multiple simultaneous alerts: each weapon ID has independent state — multiple categories can appear in HUD popups at once (deduplicated by alarm category set) (e) Beep selection across multiple active alerts: If ANY active alert is T1 (urgent) → play T1 cue Only if ALL active alerts are T2 → play T2 cue (f) On detection toggle off (S key): tracker._prev_start_state = False, baseline will be recaptured on next start (g) Session-level review: saved video file is the audit trail — operator can replay to verify each alert
B29: Algorithm (pseudocode / decision tree) | C29: # Per frame, per ROI, per baseline weapon: ON each frame: FOR each tracker (ROI): detect weapons + persons via parallel YOLO inference # UC-052 has priority — check boundary crossings first IF weapon crossed ROI boundary outbound: tracker.boundary_alerts[wid] = {label: 'UC-052(...)', frame: N} SKIP UC-051 for this weapon FOR each baseline weapon wid: is_missing = wid NOT IN current_detected_weapon_ids IF is_missing: IF state.missing_start_frame is None: state.missing_start_frame = current_frame elapsed = (current_frame - state.missing_start_frame) / video_fps # Determine proximity and locked person count proximity, locked_count, near_count = compute_proximity(wid, persons_in_roi) # PolicyEvaluator.evaluate_visibility() decision IF locked_count >= 2: IF near_count >= 2: window = ∞ (SUPPRESS); reset missing_start_frame to current_frame label = 'UC-051(C: MultiPerson→Suppress)' ELIF near_count == 1: window = T2 label = 'UC-051(C→B: OneRemains→T2)' ELSE: window = T1 label = 'UC-051(C→A: AllLeft→T1)' ELIF proximity IN ('none', 'visible'): window = T1 label = 'UC-051(A: NoPerson→T1)' ELIF proximity == 'far': window = T1 label = 'UC-051(B1: Taken→T1)' ELSE: # proximity == 'near' window = T2 label = 'UC-051(B2: Occluded→T2)' # Trigger alert if window exceeded IF elapsed >= window AND NOT state.alert_active: state.alert_active = True state.active_policy_label = label fire_alert(category, beep_type) ELSE: # weapon visible — reset all timer state state.missing_start_frame = None state.alert_active = False state.active_policy_label = None END
A30: METRICS
B31: Failure Indicators | C31: (a) >25% dismissed alerts → T1 too short, weapon retrieval occurring before expiry (b) Post-session footage shows unaccounted weapon, no alert → detection dropout or T1 too long (c) Repeated T2 expiry without person leaving → person tracking losing subjects in zone (d) Alert fires then weapon immediately reappears → T1 shorter than retrieval cycle
B32: Evaluation Method | C32: (a) Monthly staged test: all sub-scenarios, verify correct timer and alert behaviour (b) Quarterly T1/T2 threshold review based on confirmed vs dismissed alerts (c) Per-session automated log review for unresolved visibility events
B33: Evaluation Method | C33: A/B test, manual review, automated checks?
A34: DETAILED EDGE CASES | B34: Edge Case 1
B35: → Handling
B36: Edge Case 2
B37: → Handling
B38: Edge Case 3
B39: → Handling
B40: Edge Case 4
B41: → Handling
A42: TEST CASES (input → expected → rationale)
B43: Test 1: Clear match - Input
B44: → Expected response
B45: → Why correct
B46: Test 2: Ambiguous - Input
B47: → Expected response
B48: → Why correct
B49: Test 3: False positive - Input
B50: → Expected response
B51: → Why correct
A52: REVIEW & SIGN-OFF | B52: Reviewed by
B53: Review date
B54: Approved by
B55: Approval date
B56: Version | C56: 1.0
A57: OPEN ITEMS | B57: Open Questions
B58: Decisions Needed
B59: Data Gaps
B60: Next Steps

Sheet Policy - UC-052
A1: ▼ TYPE THE UC ID IN THE YELLOW CELL BELOW - EVERYTHING ELSE AUTO-FILLS ▼
B2: UC ID ↓ | C2: UC-052
A4: IDENTIFICATION | B4: Use Case Name | C4: {=IFERROR(INDEX('Use Case Library'!B:T,MATCH(C2,'Use Case Library'!B:B,0),4),"")} -> Weapon Boundary Violation (Consolidated)
B5: Group | C5: {=IFERROR(INDEX('Use Case Library'!B:T,MATCH(C2,'Use Case Library'!B:B,0),2),"")} -> J
B6: Category | C6: {=IFERROR(INDEX('Use Case Library'!B:T,MATCH(C2,'Use Case Library'!B:B,0),3),"")} -> SWT Weapons
B7: Priority | C7: {=IFERROR(INDEX('Use Case Library'!B:T,MATCH(C2,'Use Case Library'!B:B,0),12),"")} -> P0 - Critical
B8: Status | C8: {=IFERROR(INDEX('Use Case Library'!B:T,MATCH(C2,'Use Case Library'!B:B,0),13),"")} -> Draft
B9: Detection Modality | C9: {=IFERROR(INDEX('Use Case Library'!B:T,MATCH(C2,'Use Case Library'!B:B,0),16),"")}
B10: Last Updated
A11: CONTEXT (auto-pulled - edit in Use Case Library, not here)
B12: Description | C12: {=IFERROR(INDEX('Use Case Library'!B:T,MATCH(C2,'Use Case Library'!B:B,0),5),"")} -> Consolidated policy for all scenarios where a weapon crosses a restricted zone boundary, regardless of whether a person is carrying it. Person presence is captured as context but does not affect alert timing — alert is always immediate.
B13: User Intent | C13: {=IFERROR(INDEX('Use Case Library'!B:T,MATCH(C2,'Use Case Library'!B:B,0),6),"")} -> Ensure any weapon leaving its authorised zone is immediately flagged — whether carried, thrown, kicked, or otherwise moved across the boundary.
B14: Trigger / Detection Method | C14: {=IFERROR(INDEX('Use Case Library'!B:T,MATCH(C2,'Use Case Library'!B:B,0),7),"")} -> Weapon-shaped object trajectory crosses a defined restricted zone boundary line or polygon edge. Requires weapon tracked inside zone before crossing. Boundary definitions pre-loaded per exercise/zone configuration.
B15: Key Behaviours to Track | C15: {=IFERROR(INDEX('Use Case Library'!B:T,MATCH(C2,'Use Case Library'!B:B,0),8),"")} -> 1) Weapon position relative to zone boundary (inside / crossing / outside) 2) Weapon trajectory vector at crossing 3) Person association status at crossing (context only) 4) Crossing speed and direction 5) Whether weapon returns inside boundary after crossing
B16: Desired Outcome | C16: {=IFERROR(INDEX('Use Case Library'!B:T,MATCH(C2,'Use Case Library'!B:B,0),9),"")} -> Immediate alert the moment weapon crosses the restricted boundary. No grace period, no timer. Alert remains active until operator acknowledges. Highest priority — overrides UC-051 timers if both conditions occur simultaneously.
B17: Current Handling | C17: {=IFERROR(INDEX('Use Case Library'!B:T,MATCH(C2,'Use Case Library'!B:B,0),10),"")} -> Manual observation. No automated boundary monitoring or crossing detection.
B18: Edge Cases (from library) | C18: {=IFERROR(INDEX('Use Case Library'!B:T,MATCH(C2,'Use Case Library'!B:B,0),11),"")} -> - Weapon bouncing across boundary and returning (transient crossing) - Camera parallax causing apparent crossing that did not occur - Multiple weapons near boundary simultaneously - Authorised staff repositioning weapon across boundary
B19: Dependencies | C19: {=IFERROR(INDEX('Use Case Library'!B:T,MATCH(C2,'Use Case Library'!B:B,0),15),"")} -> Zone boundary definitions (pre-loaded per exercise). UC-051 (Weapon Visibility Rule).
B20: Current Policy Summary | C20: {=IFERROR(INDEX('Use Case Library'!B:T,MATCH(C2,'Use Case Library'!B:B,0),14),"")} -> IF weapon crosses restricted zone boundary → IMMEDIATE alert (no timer, no delay). Person association is logged as context but does not suppress or delay the alert. Alert remains active until operator acknowledges. HIGHEST PRIORITY — overrides all UC-051 (Visibility) timers if both conditions occur simultaneously.
B21: Modality Rationale | C21: {=IFERROR(INDEX('Use Case Library'!B:T,MATCH(C2,'Use Case Library'!B:B,0),17),"")} -> Visual Only
A22: DECISION LOGIC (fill manually - core deliverable)
B23: Step 1: Detection | C23: The system maintains a per-weapon previous-frame ROI containment flag (tracker.weapon_prev_inside[wid]) for every tracked weapon. Each frame, the weapon's CENTER point is tested against the ROI polygon using cv2.pointPolygonTest with a bounding-box pre-filter for speed. Signals that activate this use case: - A weapon's center transitions from INSIDE the ROI polygon (previous frame) to OUTSIDE the ROI polygon (current frame) - The weapon must be currently detected (visible) for crossing to register — an undetected weapon defers to UC-051 ROI configuration: - ROI polygons loaded at startup from roi_coord/{video_name}.json - Coordinates stored normalized (0-1) relative to original frame size, denormalized at load - Supports multi-ROI per camera (each ROI has its own ROITracker instance) - Bounding box of polygon is cached for fast point-in-polygon pre-filtering Configurable thresholds (credentials.json): - WEAPON_CONFIDENCE_THRESHOLD = 0.25 - ASSOCIATION_DISTANCE (used only to determine person-association context at crossing) - No timer thresholds — UC-052 is always immediate (T1 = 0)
B24: Step 2: Classification | C24: All boundary crossings are CRITICAL severity — no severity gradation. Any outbound boundary crossing is equally unacceptable regardless of speed, distance, or person association. Person association at crossing is captured for incident context only (does NOT affect alert timing): ASSOCIATED — a person was detected within ASSOCIATION_DISTANCE of the weapon's last known position at crossing time → label = 'UC-052(Movement: Associated→IMMEDIATE)' → Most likely: weapon was carried deliberately across the boundary UNASSOCIATED — no person was within ASSOCIATION_DISTANCE of the weapon at crossing → label = 'UC-052(Movement: Unassociated→IMMEDIATE)' → Most likely: weapon was thrown, kicked, or slid across the boundary Inbound crossings (OUTSIDE → INSIDE) are logged but NOT alerted — only outbound crossings trigger alerts.
B25: Step 3: Response Selection | C25: PolicyEvaluator.evaluate_movement(prev_inside, curr_inside, has_person_associated) returns (immediate_alert, label): IF prev_inside == True AND curr_inside == False: immediate_alert = True label = 'UC-052(Movement: Associated→IMMEDIATE)' if has_person else 'UC-052(Movement: Unassociated→IMMEDIATE)' ELSE: immediate_alert = False (no crossing, or inbound) ALL crossings → IMMEDIATE alert. No timer. No grace period. No conditions. UC-052 HAS HIGHEST PRIORITY: - If a weapon has a pending boundary alert in tracker.boundary_alerts, UC-051 evaluation is SKIPPED for that weapon - Boundary alert persists in tracker.boundary_alerts until baseline is recaptured (operator equivalent of acknowledgement)
B26: Step 4: Execution | C26: On outbound boundary crossing detection (in _check_boundary_crossings): 1. Add entry to tracker.boundary_alerts[wid]: {'label': '<UC-052 label>', 'frame': current_frame, 'associated': bool} 2. In _process_roi_detections, the boundary alert is detected BEFORE UC-051 timer logic: state_w['alert_active'] = True state_w['alert_start_frame'] = boundary_alert.frame state_w['active_policy_label'] = boundary_alert.label 3. HUD popup added with category 'Weapon Boundary Violation' (mapped via PolicyEvaluator.alarm_category_for_label) 4. Audio cue: beep_type = 0 → alert_T1.wav (always urgent, never T2) 5. Draw MAGENTA dashed box at last known position with label 'BOUNDARY ID{wid}' (distinct from yellow missing boxes used by UC-051) 6. Console log entry: [UC-052] ROI {roi_id} Weapon {wid} BOUNDARY VIOLATION | {label} | associated={bool} | frame={N} 7. Annotated frame written to saved video output if enabled 8. Update tracker.weapon_prev_inside[wid] = False so the next frame's check uses correct state
B27: Step 5: Validation | C27: Pre-alert validation (inside _check_boundary_crossings): (a) Polygon required — if tracker.polygon is None (full-frame mode), UC-052 evaluation is skipped (no boundary defined) (b) Movement policy must be enabled — self.policy.movement_enabled must be True (c) Weapon must be currently visible — if wid not in weapons_by_id (detected this frame), UC-052 cannot confirm a crossing for this frame; prev_inside is NOT updated, deferring to UC-051 (d) Person association resolved at last known position (tracker.last_known_stationary_boxes[wid]) when available, falling back to current detected center Post-alert: (a) tracker.boundary_alerts[wid] persists across frames — the alert is not auto-cleared by re-entry (b) Per UC-052 spec, alert remains until operator acknowledgement; current implementation treats baseline recapture (detection toggle OFF → ON) as implicit acknowledgement (c) If weapon re-enters ROI while alert is pending, prev_inside flips back to True but the existing boundary_alert entry is unaffected
B28: Step 6: Follow-up | C28: After boundary violation alert: (a) Boundary alert badge persists on HUD until operator stops/restarts detection (clears tracker state via reset_baseline) (b) Magenta dashed box remains drawn at last known weapon position even if weapon is no longer detected (c) Console log preserves the crossing event with full context (ROI, weapon ID, frame, person association) (d) Saved video file contains the crossing moment, providing audit trail with trajectory visible (e) Multiple simultaneous violations: each weapon ID has its own entry in tracker.boundary_alerts — multiple weapons crossing the same or different boundaries fire independent alerts (f) UC-052 alarm category 'Weapon Boundary Violation' is shown distinctly in the HUD popup list, separate from UC-051 categories (g) Beep priority: any UC-052 alert always wins beep selection (T1 cue) over UC-051 T2 cues, ensuring boundary violations are sonically distinct from occlusion warnings (h) Operator acknowledgement = pressing S to stop detection, then S to start again (this clears tracker.boundary_alerts via baseline recapture)
B29: Algorithm (pseudocode / decision tree) | C29: # UC-052 boundary crossing check — runs FIRST every frame, before UC-051 ON EXERCISE_START / detection enabled: LOAD ROI polygons from roi_coord/{video_name}.json FOR each weapon in baseline: tracker.weapon_prev_inside[wid] = True # baseline is inside ROI by definition ON each frame (in _check_boundary_crossings): IF tracker.polygon is None OR NOT policy.movement_enabled: RETURN [] # skip — no boundary to monitor weapons_by_id = {b[6]: b for b in all_weapon_boxes if b[6] is not None} candidate_ids = visible_weapon_ids ∪ prev_inside_keys ∪ baseline_ids FOR each wid in candidate_ids: prev_inside = tracker.weapon_prev_inside.get(wid, False) IF wid NOT IN weapons_by_id: # Weapon not visible this frame — UC-051 handles it, do NOT update prev_inside CONTINUE wbox = weapons_by_id[wid] curr_inside = tracker.point_in_roi_fast(wbox.center) # Resolve person association ONLY at crossing moment has_person = False IF curr_inside == False AND prev_inside == True: # outbound crossing w_center = tracker.last_known_stationary_boxes.get(wid, wbox.center) FOR p_box in persons_in_roi: IF distance(p_box.center, w_center) <= ASSOCIATION_DISTANCE: has_person = True BREAK # Delegate decision to PolicyEvaluator.evaluate_movement() fires, label = policy.evaluate_movement(prev_inside, curr_inside, has_person) IF fires AND wid NOT IN tracker.boundary_alerts: tracker.boundary_alerts[wid] = { 'label': label, 'frame': tracker.frame_count, 'associated': has_person } LOG '[UC-052] BOUNDARY VIOLATION ...' tracker.weapon_prev_inside[wid] = curr_inside # update for next frame # Then in main per-weapon loop in _process_roi_detections: FOR each wid in baseline: IF wid IN tracker.boundary_alerts: ba = tracker.boundary_alerts[wid] state.alert_active = True state.active_policy_label = ba.label CONTINUE # UC-052 wins — skip UC-051 for this weapon # ... else fall through to UC-051 timer evaluation ...
A30: METRICS
B31: Failure Indicators | C31: (a) Any staged crossing test produces a miss → immediate failure investigation (b) False positive rate >15% at specific boundary segment → calibration/parallax issue (c) Alert latency >2s → tracking pipeline delay (d) Operator mass-acknowledging without review → alert fatigue from false positives
